{"nexml": {"@xmlns": {"xsd": "http://www.w3.org/2001/XMLSchema#", "xsi": "http://www.w3.org/2001/XMLSchema-instance", "$": "http://www.nexml.org/2009", "nex": "http://www.nexml.org/2009", "ot": "http://purl.org/opentree-terms#"}, "@about": "#study", "@nexmljson": "http://opentree.wikispaces.com/NexSON", "meta": [{"@property": "ot:studyPublicationReference", "@xsi:type": "nex:LiteralMeta", "$": "Rossman A., Schoch C.L., Farr D., Nishijima K., Keith L., & Goenaga R. 2010. Dolabra nepheliae on rambutan and lychee represents a novel lineage of phytopathogenic Eurotiomycetes. Mycoscience, 51(4), 300-309."}, {"@property": "ot:studyPublication", "@xsi:type": "nex:ResourceMeta", "@href": "http://dx.doi.org/10.1007/s10267-010-0042-y"}, {"@property": "ot:curatorName", "@xsi:type": "nex:LiteralMeta", "$": "Romina Gazis"}, {"@property": "ot:dataDeposit", "@xsi:type": "nex:ResourceMeta", "@href": "http://purl.org/phylo/treebase/phylows/study/TB2:S10234"}, {"@property": "ot:studyId", "@xsi:type": "nex:LiteralMeta", "$": "1043"}, {"@property": "ot:studyYear", "@xsi:type": "nex:LiteralMeta", "$": 2010}, {"@property": "ot:focalClade", "@xsi:type": "nex:LiteralMeta", "$": 815382}, {"@property": "ot:tag", "@xsi:type": "nex:LiteralMeta", "$": "ML"}, {"@property": "ot:tag", "@xsi:type": "nex:LiteralMeta", "$": "MP"}, {"@property": "ot:tag", "@xsi:type": "nex:LiteralMeta", "$": "LSU"}, {"@property": "ot:tag", "@xsi:type": "nex:LiteralMeta", "$": "RPB2"}, {"@property": "ot:tag", "@xsi:type": "nex:LiteralMeta", "$": "EF-1"}], "@generator": "Phylografter nexml-json exporter", "@version": "0.9", "@id": "study", "otus": {"@id": "otus1043", "otu": [{"@label": "Ramichloridium anceps", "meta": [{"@property": "ot:ottolid", "@xsi:type": "nex:LiteralMeta", "$": 888563}, {"@property": "ot:originalLabel", "@xsi:type": "nex:LiteralMeta", "$": "Ramichloridium anceps AFTOL 659"}], "@id": "otu216192", "@about": "#otu216192"}, {"@label": "Dolabra nepheliae", "meta": [{"@property": "ot:ottolid", "@xsi:type": "nex:LiteralMeta", "$": 483207}, {"@property": "ot:originalLabel", "@xsi:type": "nex:LiteralMeta", "$": "Dolabra nepheliae CBS 122119"}], "@id": "otu216193", "@about": "#otu216193"}, {"@label": "Capronia munkii", "meta": [{"@property": "ot:ottolid", "@xsi:type": "nex:LiteralMeta", "$": 56765}, {"@property": "ot:originalLabel", "@xsi:type": "nex:LiteralMeta", "$": "Capronia munkii AFTOL 656"}], "@id": "otu216194", "@about": "#otu216194"}, {"@label": "Exophiala dermatitidis", "meta": [{"@property": "ot:ottolid", "@xsi:type": "nex:LiteralMeta", "$": 129117}, {"@property": "ot:originalLabel", "@xsi:type": "nex:LiteralMeta", "$": "Exophiala dermatitidis AFTOL 668"}], "@id": "otu216195", "@about": "#otu216195"}, {"@label": "Chaetothyriomycetidae", "meta": [{"@property": "ot:ottolid", "@xsi:type": "nex:LiteralMeta", "$": 81982}, {"@property": "ot:originalLabel", "@xsi:type": "nex:LiteralMeta", "$": "Endophyte 4466"}], "@id": "otu216196", "@about": "#otu216196"}, {"@label": "Pyrenula pseudobufonia", "meta": [{"@property": "ot:ottolid", "@xsi:type": "nex:LiteralMeta", "$": 767394}, {"@property": "ot:originalLabel", "@xsi:type": "nex:LiteralMeta", "$": "Pyrenula pseudobufonia AFTOL 387"}], "@id": "otu216197", "@about": "#otu216197"}, {"@label": "Dolabra nepheliae", "meta": [{"@property": "ot:ottolid", "@xsi:type": "nex:LiteralMeta", "$": 483207}, {"@property": "ot:originalLabel", "@xsi:type": "nex:LiteralMeta", "$": "Dolabra nepheliae CBS 122120"}], "@id": "otu216198", "@about": "#otu216198"}, {"@label": "Cyphellophora laciniata", "meta": [{"@property": "ot:ottolid", "@xsi:type": "nex:LiteralMeta", "$": 1024674}, {"@property": "ot:originalLabel", "@xsi:type": "nex:LiteralMeta", "$": "Cyphellophora laciniata AFTOL 1033"}], "@id": "otu216199", "@about": "#otu216199"}, {"@label": "Chaetothyriales", "meta": [{"@property": "ot:ottolid", "@xsi:type": "nex:LiteralMeta", "$": 537959}, {"@property": "ot:originalLabel", "@xsi:type": "nex:LiteralMeta", "$": "Endophyte 422"}], "@id": "otu216200", "@about": "#otu216200"}, {"@label": "Ceramothyrium carniolicum", "meta": [{"@property": "ot:ottolid", "@xsi:type": "nex:LiteralMeta", "$": 597882}, {"@property": "ot:originalLabel", "@xsi:type": "nex:LiteralMeta", "$": "Ceramothyrium carniolicum AFTOL 1063"}], "@id": "otu216201", "@about": "#otu216201"}, {"@label": "Endocarpon pallidulum", "meta": [{"@property": "ot:ottolid", "@xsi:type": "nex:LiteralMeta", "$": 940869}, {"@property": "ot:originalLabel", "@xsi:type": "nex:LiteralMeta", "$": "Endocarpon pallidulum AFTOL 661"}], "@id": "otu216202", "@about": "#otu216202"}, {"@label": "Pyrenula aspistea", "meta": [{"@property": "ot:ottolid", "@xsi:type": "nex:LiteralMeta", "$": 704493}, {"@property": "ot:originalLabel", "@xsi:type": "nex:LiteralMeta", "$": "Pyrenula aspistea AFTOL 623"}], "@id": "otu216203", "@about": "#otu216203"}, {"@label": "Granulopyrenis seawardii", "meta": [{"@property": "ot:ottolid", "@xsi:type": "nex:LiteralMeta", "$": 905566}, {"@property": "ot:originalLabel", "@xsi:type": "nex:LiteralMeta", "$": "Granulopyrenis seawardi AFTOL 612"}], "@id": "otu216204", "@about": "#otu216204"}, {"@label": "Capronia pilosella", "meta": [{"@property": "ot:ottolid", "@xsi:type": "nex:LiteralMeta", "$": 666121}, {"@property": "ot:originalLabel", "@xsi:type": "nex:LiteralMeta", "$": "Capronia pilosella AFTOL 657"}], "@id": "otu216205", "@about": "#otu216205"}, {"@label": "Agonimia", "meta": [{"@property": "ot:ottolid", "@xsi:type": "nex:LiteralMeta", "$": 741451}, {"@property": "ot:originalLabel", "@xsi:type": "nex:LiteralMeta", "$": "Agonimia sp AFTOL 684"}], "@id": "otu216206", "@about": "#otu216206"}, {"@label": "Dermatocarpon miniatum", "meta": [{"@property": "ot:ottolid", "@xsi:type": "nex:LiteralMeta", "$": 440205}, {"@property": "ot:originalLabel", "@xsi:type": "nex:LiteralMeta", "$": "Dermatocarpon miniatum AFTOL 91"}], "@id": "otu216207", "@about": "#otu216207"}, {"@label": "Sphinctrina turbinata", "meta": [{"@property": "ot:ottolid", "@xsi:type": "nex:LiteralMeta", "$": 344366}, {"@property": "ot:originalLabel", "@xsi:type": "nex:LiteralMeta", "$": "Sphinctrina turbinata AFTOL 1721"}], "@id": "otu216208", "@about": "#otu216208"}, {"@label": "Sarcinomyces petricola", "meta": [{"@property": "ot:ottolid", "@xsi:type": "nex:LiteralMeta", "$": 158875}, {"@property": "ot:originalLabel", "@xsi:type": "nex:LiteralMeta", "$": "Sarcinomyces petricola AFTOL 825"}], "@id": "otu216209", "@about": "#otu216209"}, {"@label": "Phaeoacremonium chlamydosporum", "meta": [{"@property": "ot:ottolid", "@xsi:type": "nex:LiteralMeta", "$": 271803}, {"@property": "ot:originalLabel", "@xsi:type": "nex:LiteralMeta", "$": "Phaeoacremonium chlamydosporum CBS 229 95"}], "@id": "otu216210", "@about": "#otu216210"}, {"@label": "Dolabra nepheliae", "meta": [{"@property": "ot:ottolid", "@xsi:type": "nex:LiteralMeta", "$": 483207}, {"@property": "ot:originalLabel", "@xsi:type": "nex:LiteralMeta", "$": "Dolabra nepheliae CBS 123297"}], "@id": "otu216211", "@about": "#otu216211"}, {"@label": "Staurothele frustulenta", "meta": [{"@property": "ot:ottolid", "@xsi:type": "nex:LiteralMeta", "$": 940868}, {"@property": "ot:originalLabel", "@xsi:type": "nex:LiteralMeta", "$": "Staurothele frustulenta AFTOL 697"}], "@id": "otu216212", "@about": "#otu216212"}, {"@label": "Caliciopsis orientalis", "meta": [{"@property": "ot:ottolid", "@xsi:type": "nex:LiteralMeta", "$": 812159}, {"@property": "ot:originalLabel", "@xsi:type": "nex:LiteralMeta", "$": "Caliciopsis orientalis AFTOL 1911"}], "@id": "otu216213", "@about": "#otu216213"}, {"@label": "Lithothelium septemseptatum", "meta": [{"@property": "ot:ottolid", "@xsi:type": "nex:LiteralMeta", "$": 767386}, {"@property": "ot:originalLabel", "@xsi:type": "nex:LiteralMeta", "$": "Lithothelium septemseptatum AFTOL 12"}], "@id": "otu216214", "@about": "#otu216214"}, {"@label": "Aspergillus nidulans", "meta": [{"@property": "ot:ottolid", "@xsi:type": "nex:LiteralMeta", "$": 392368}, {"@property": "ot:originalLabel", "@xsi:type": "nex:LiteralMeta", "$": "Aspergillus nidulans AFTOL 1080"}], "@id": "otu216215", "@about": "#otu216215"}, {"@label": "Ajellomyces capsulatus", "meta": [{"@property": "ot:ottolid", "@xsi:type": "nex:LiteralMeta", "$": 124563}, {"@property": "ot:originalLabel", "@xsi:type": "nex:LiteralMeta", "$": "Histoplasma capsulatum AFTOL 1083"}], "@id": "otu216216", "@about": "#otu216216"}, {"@label": "Exophiala pisciphila", "meta": [{"@property": "ot:ottolid", "@xsi:type": "nex:LiteralMeta", "$": 274726}, {"@property": "ot:originalLabel", "@xsi:type": "nex:LiteralMeta", "$": "Exophiala pisciphila AFTOL 669"}], "@id": "otu216217", "@about": "#otu216217"}, {"@label": "Chaetothyriales", "meta": [{"@property": "ot:ottolid", "@xsi:type": "nex:LiteralMeta", "$": 537959}, {"@property": "ot:originalLabel", "@xsi:type": "nex:LiteralMeta", "$": "rock isolate TRN488"}], "@id": "otu216218", "@about": "#otu216218"}, {"@label": "Spiromastix warcupii", "meta": [{"@property": "ot:ottolid", "@xsi:type": "nex:LiteralMeta", "$": 658627}, {"@property": "ot:originalLabel", "@xsi:type": "nex:LiteralMeta", "$": "Spiromastix warcupii AFTOL 430"}], "@id": "otu216219", "@about": "#otu216219"}, {"@label": "Chaetothyriales", "meta": [{"@property": "ot:ottolid", "@xsi:type": "nex:LiteralMeta", "$": 537959}, {"@property": "ot:originalLabel", "@xsi:type": "nex:LiteralMeta", "$": "rock isolate TRN475"}], "@id": "otu216220", "@about": "#otu216220"}, {"@label": "Chaetothyriales", "meta": [{"@property": "ot:ottolid", "@xsi:type": "nex:LiteralMeta", "$": 537959}, {"@property": "ot:originalLabel", "@xsi:type": "nex:LiteralMeta", "$": "rock isolate A95"}], "@id": "otu216221", "@about": "#otu216221"}, {"@label": "Geoglossum nigritum", "meta": [{"@property": "ot:ottolid", "@xsi:type": "nex:LiteralMeta", "$": 950343}, {"@property": "ot:originalLabel", "@xsi:type": "nex:LiteralMeta", "$": "Geoglossum nigritum AFTOL 56"}], "@id": "otu216222", "@about": "#otu216222"}, {"@label": "Dactylospora haliotrepha", "meta": [{"@property": "ot:ottolid", "@xsi:type": "nex:LiteralMeta", "$": 819780}, {"@property": "ot:originalLabel", "@xsi:type": "nex:LiteralMeta", "$": "Dactylospora haliotrepha AFTOL 186"}], "@id": "otu216223", "@about": "#otu216223"}, {"@label": "Monascus purpureus", "meta": [{"@property": "ot:ottolid", "@xsi:type": "nex:LiteralMeta", "$": 376359}, {"@property": "ot:originalLabel", "@xsi:type": "nex:LiteralMeta", "$": "Monascus purpureus AFTOL 426"}], "@id": "otu216224", "@about": "#otu216224"}, {"@label": "Eupenicillium limosum", "meta": [{"@property": "ot:ottolid", "@xsi:type": "nex:LiteralMeta", "$": 181097}, {"@property": "ot:originalLabel", "@xsi:type": "nex:LiteralMeta", "$": "Eupenicillium limosum AFTOL 564"}], "@id": "otu216225", "@about": "#otu216225"}, {"@label": "Anthracothecium nanum", "meta": [{"@property": "ot:ottolid", "@xsi:type": "nex:LiteralMeta", "$": 312096}, {"@property": "ot:originalLabel", "@xsi:type": "nex:LiteralMeta", "$": "Ahracothecium nanum AFTOL 1649"}], "@id": "otu216226", "@about": "#otu216226"}, {"@label": "Exophiala salmonis", "meta": [{"@property": "ot:ottolid", "@xsi:type": "nex:LiteralMeta", "$": 1051945}, {"@property": "ot:originalLabel", "@xsi:type": "nex:LiteralMeta", "$": "Exophiala salmonis AFTOL 671"}], "@id": "otu216227", "@about": "#otu216227"}, {"@label": "Penicillium freii", "meta": [{"@property": "ot:ottolid", "@xsi:type": "nex:LiteralMeta", "$": 998167}, {"@property": "ot:originalLabel", "@xsi:type": "nex:LiteralMeta", "$": "Penicillium freii AFTOL 378"}], "@id": "otu216228", "@about": "#otu216228"}, {"@label": "Chaetothyriales", "meta": [{"@property": "ot:ottolid", "@xsi:type": "nex:LiteralMeta", "$": 537959}, {"@property": "ot:originalLabel", "@xsi:type": "nex:LiteralMeta", "$": "rock isolate TRN214"}], "@id": "otu216229", "@about": "#otu216229"}, {"@label": "Coccidioides immitis", "meta": [{"@property": "ot:ottolid", "@xsi:type": "nex:LiteralMeta", "$": 838981}, {"@property": "ot:originalLabel", "@xsi:type": "nex:LiteralMeta", "$": "Coccidioides immitis AFTOL 1084"}], "@id": "otu216230", "@about": "#otu216230"}, {"@label": "Pyrgillus javanicus", "meta": [{"@property": "ot:ottolid", "@xsi:type": "nex:LiteralMeta", "$": 67600}, {"@property": "ot:originalLabel", "@xsi:type": "nex:LiteralMeta", "$": "Pyrgillus javanicus AFTOL 342"}], "@id": "otu216231", "@about": "#otu216231"}, {"@label": "Polyblastia melaspora", "meta": [{"@property": "ot:ottolid", "@xsi:type": "nex:LiteralMeta", "$": 954145}, {"@property": "ot:originalLabel", "@xsi:type": "nex:LiteralMeta", "$": "Polyblastia melaspora AFTOL 1356"}], "@id": "otu216232", "@about": "#otu216232"}, {"@label": "Chaetothyriomycetidae", "meta": [{"@property": "ot:ottolid", "@xsi:type": "nex:LiteralMeta", "$": 81982}, {"@property": "ot:originalLabel", "@xsi:type": "nex:LiteralMeta", "$": "rock isolate TRN242"}], "@id": "otu216233", "@about": "#otu216233"}, {"@label": "Chaetothyriomycetidae", "meta": [{"@property": "ot:ottolid", "@xsi:type": "nex:LiteralMeta", "$": 81982}, {"@property": "ot:originalLabel", "@xsi:type": "nex:LiteralMeta", "$": "rock isolate A14"}], "@id": "otu216234", "@about": "#otu216234"}, {"@label": "Wahlenbergiella mucosa", "meta": [{"@property": "ot:ottolid", "@xsi:type": "nex:LiteralMeta", "$": 718630}, {"@property": "ot:originalLabel", "@xsi:type": "nex:LiteralMeta", "$": "Wahlenbergiella mucosa AFTOL 2264"}], "@id": "otu216235", "@about": "#otu216235"}, {"@label": "Chaetothyriales", "meta": [{"@property": "ot:ottolid", "@xsi:type": "nex:LiteralMeta", "$": 537959}, {"@property": "ot:originalLabel", "@xsi:type": "nex:LiteralMeta", "$": "rock isolate TRN107"}], "@id": "otu216236", "@about": "#otu216236"}, {"@label": "Caliciopsis pinea", "meta": [{"@property": "ot:ottolid", "@xsi:type": "nex:LiteralMeta", "$": 123355}, {"@property": "ot:originalLabel", "@xsi:type": "nex:LiteralMeta", "$": "Caliciopsis pinea AFTOL 1869"}], "@id": "otu216237", "@about": "#otu216237"}, {"@label": "Aspergillus fumigatus", "meta": [{"@property": "ot:ottolid", "@xsi:type": "nex:LiteralMeta", "$": 278828}, {"@property": "ot:originalLabel", "@xsi:type": "nex:LiteralMeta", "$": "Aspergillus fumigatus AFTOL 1079"}], "@id": "otu216238", "@about": "#otu216238"}, {"@label": "Dactylospora mangrovei", "meta": [{"@property": "ot:ottolid", "@xsi:type": "nex:LiteralMeta", "$": 1086863}, {"@property": "ot:originalLabel", "@xsi:type": "nex:LiteralMeta", "$": "Dactylospora mangrovei AFTOL 832"}], "@id": "otu216239", "@about": "#otu216239"}, {"@label": "Eupenicillium javanicum", "meta": [{"@property": "ot:ottolid", "@xsi:type": "nex:LiteralMeta", "$": 589692}, {"@property": "ot:originalLabel", "@xsi:type": "nex:LiteralMeta", "$": "Eupenicillium javanicum AFTOL 429"}], "@id": "otu216240", "@about": "#otu216240"}, {"@label": "Chaetothyriales", "meta": [{"@property": "ot:ottolid", "@xsi:type": "nex:LiteralMeta", "$": 537959}, {"@property": "ot:originalLabel", "@xsi:type": "nex:LiteralMeta", "$": "rock isolate TRN508"}], "@id": "otu216241", "@about": "#otu216241"}]}, "trees": {"@id": "trees1043", "@otus": "otus1043", "tree": [{"node": [{"@id": "node509596", "@root": "true"}, {"@otu": "otu216208", "@id": "node509597"}, {"@id": "node509598"}, {"@id": "node509599"}, {"@id": "node509600"}, {"@id": "node509601"}, {"@otu": "otu216199", "@id": "node509602"}, {"@otu": "otu216201", "@id": "node509603"}, {"@id": "node509604"}, {"@otu": "otu216209", "@id": "node509605"}, {"@id": "node509606"}, {"@otu": "otu216200", "@id": "node509607"}, {"@id": "node509608"}, {"@id": "node509609"}, {"@otu": "otu216194", "@id": "node509610"}, {"@otu": "otu216195", "@id": "node509611"}, {"@id": "node509612"}, {"@otu": "otu216205", "@id": "node509613"}, {"@otu": "otu216192", "@id": "node509614"}, {"@id": "node509615"}, {"@id": "node509616"}, {"@otu": "otu216193", "@id": "node509617"}, {"@id": "node509618"}, {"@otu": "otu216198", "@id": "node509619"}, {"@otu": "otu216211", "@id": "node509620"}, {"@id": "node509621"}, {"@otu": "otu216196", "@id": "node509622"}, {"@otu": "otu216210", "@id": "node509623"}, {"@id": "node509624"}, {"@id": "node509625"}, {"@otu": "otu216202", "@id": "node509626"}, {"@otu": "otu216207", "@id": "node509627"}, {"@id": "node509628"}, {"@otu": "otu216206", "@id": "node509629"}, {"@otu": "otu216212", "@id": "node509630"}, {"@id": "node509631"}, {"@otu": "otu216203", "@id": "node509632"}, {"@id": "node509633"}, {"@otu": "otu216197", "@id": "node509634"}, {"@otu": "otu216204", "@id": "node509635"}], "@about": "#tree1998", "meta": [{"@property": "ot:inGroupClade", "@xsi:type": "nex:LiteralMeta", "$": "node509598"}, {"@property": "ot:tag", "@xsi:type": "nex:LiteralMeta", "$": "MP"}, {"@property": "ot:tag", "@xsi:type": "nex:LiteralMeta", "$": "LSU"}], "edge": [{"@source": "node509596", "@target": "node509597", "@id": "edge509597"}, {"@source": "node509596", "@target": "node509598", "@id": "edge509598"}, {"@source": "node509598", "@target": "node509599", "@id": "edge509599"}, {"@source": "node509599", "@target": "node509600", "@id": "edge509600"}, {"@source": "node509600", "@target": "node509601", "@id": "edge509601"}, {"@source": "node509601", "@target": "node509602", "@id": "edge509602"}, {"@source": "node509601", "@target": "node509603", "@id": "edge509603"}, {"@source": "node509600", "@target": "node509604", "@id": "edge509604"}, {"@source": "node509604", "@target": "node509605", "@id": "edge509605"}, {"@source": "node509604", "@target": "node509606", "@id": "edge509606"}, {"@source": "node509606", "@target": "node509607", "@id": "edge509607"}, {"@source": "node509606", "@target": "node509608", "@id": "edge509608"}, {"@source": "node509608", "@target": "node509609", "@id": "edge509609"}, {"@source": "node509609", "@target": "node509610", "@id": "edge509610"}, {"@source": "node509609", "@target": "node509611", "@id": "edge509611"}, {"@source": "node509608", "@target": "node509612", "@id": "edge509612"}, {"@source": "node509612", "@target": "node509613", "@id": "edge509613"}, {"@source": "node509612", "@target": "node509614", "@id": "edge509614"}, {"@source": "node509599", "@target": "node509615", "@id": "edge509615"}, {"@source": "node509615", "@target": "node509616", "@id": "edge509616"}, {"@source": "node509616", "@target": "node509617", "@id": "edge509617"}, {"@source": "node509616", "@target": "node509618", "@id": "edge509618"}, {"@source": "node509618", "@target": "node509619", "@id": "edge509619"}, {"@source": "node509618", "@target": "node509620", "@id": "edge509620"}, {"@source": "node509615", "@target": "node509621", "@id": "edge509621"}, {"@source": "node509621", "@target": "node509622", "@id": "edge509622"}, {"@source": "node509621", "@target": "node509623", "@id": "edge509623"}, {"@source": "node509598", "@target": "node509624", "@id": "edge509624"}, {"@source": "node509624", "@target": "node509625", "@id": "edge509625"}, {"@source": "node509625", "@target": "node509626", "@id": "edge509626"}, {"@source": "node509625", "@target": "node509627", "@id": "edge509627"}, {"@source": "node509624", "@target": "node509628", "@id": "edge509628"}, {"@source": "node509628", "@target": "node509629", "@id": "edge509629"}, {"@source": "node509628", "@target": "node509630", "@id": "edge509630"}, {"@source": "node509596", "@target": "node509631", "@id": "edge509631"}, {"@source": "node509631", "@target": "node509632", "@id": "edge509632"}, {"@source": "node509631", "@target": "node509633", "@id": "edge509633"}, {"@source": "node509633", "@target": "node509634", "@id": "edge509634"}, {"@source": "node509633", "@target": "node509635", "@id": "edge509635"}], "@id": "tree1998"}, {"node": [{"@id": "node509636", "@root": "true"}, {"@otu": "otu216222", "@id": "node509637"}, {"@id": "node509638"}, {"@otu": "otu216208", "@id": "node509639"}, {"@id": "node509640"}, {"@id": "node509641"}, {"@id": "node509642"}, {"@otu": "otu216213", "@id": "node509643"}, {"@otu": "otu216237", "@id": "node509644"}, {"@id": "node509645"}, {"@id": "node509646"}, {"@otu": "otu216230", "@id": "node509647"}, {"@id": "node509648"}, {"@otu": "otu216219", "@id": "node509649"}, {"@otu": "otu216216", "@id": "node509650"}, {"@id": "node509651"}, {"@otu": "otu216238", "@id": "node509652"}, {"@id": "node509653"}, {"@otu": "otu216215", "@id": "node509654"}, {"@id": "node509655"}, {"@otu": "otu216224", "@id": "node509656"}, {"@id": "node509657"}, {"@otu": "otu216228", "@id": "node509658"}, {"@id": "node509659"}, {"@otu": "otu216225", "@id": "node509660"}, {"@otu": "otu216240", "@id": "node509661"}, {"@id": "node509662"}, {"@id": "node509663"}, {"@id": "node509664"}, {"@id": "node509665"}, {"@id": "node509666"}, {"@id": "node509667"}, {"@id": "node509668"}, {"@id": "node509669"}, {"@otu": "otu216201", "@id": "node509670"}, {"@id": "node509671"}, {"@otu": "otu216236", "@id": "node509672"}, {"@id": "node509673"}, {"@otu": "otu216199", "@id": "node509674"}, {"@otu": "otu216229", "@id": "node509675"}, {"@id": "node509676"}, {"@otu": "otu216209", "@id": "node509677"}, {"@otu": "otu216221", "@id": "node509678"}, {"@id": "node509679"}, {"@otu": "otu216241", "@id": "node509680"}, {"@id": "node509681"}, {"@otu": "otu216192", "@id": "node509682"}, {"@id": "node509683"}, {"@otu": "otu216195", "@id": "node509684"}, {"@id": "node509685"}, {"@otu": "otu216217", "@id": "node509686"}, {"@otu": "otu216227", "@id": "node509687"}, {"@id": "node509688"}, {"@otu": "otu216220", "@id": "node509689"}, {"@otu": "otu216218", "@id": "node509690"}, {"@id": "node509691"}, {"@id": "node509692"}, {"@otu": "otu216234", "@id": "node509693"}, {"@otu": "otu216233", "@id": "node509694"}, {"@id": "node509695"}, {"@otu": "otu216235", "@id": "node509696"}, {"@id": "node509697"}, {"@id": "node509698"}, {"@otu": "otu216206", "@id": "node509699"}, {"@otu": "otu216212", "@id": "node509700"}, {"@id": "node509701"}, {"@otu": "otu216232", "@id": "node509702"}, {"@id": "node509703"}, {"@otu": "otu216207", "@id": "node509704"}, {"@otu": "otu216202", "@id": "node509705"}, {"@id": "node509706"}, {"@otu": "otu216210", "@id": "node509707"}, {"@id": "node509708"}, {"@otu": "otu216196", "@id": "node509709"}, {"@id": "node509710"}, {"@otu": "otu216193", "@id": "node509711"}, {"@id": "node509712"}, {"@otu": "otu216211", "@id": "node509713"}, {"@otu": "otu216198", "@id": "node509714"}, {"@id": "node509715"}, {"@id": "node509716"}, {"@otu": "otu216214", "@id": "node509717"}, {"@id": "node509718"}, {"@otu": "otu216197", "@id": "node509719"}, {"@otu": "otu216226", "@id": "node509720"}, {"@id": "node509721"}, {"@otu": "otu216203", "@id": "node509722"}, {"@otu": "otu216231", "@id": "node509723"}, {"@id": "node509724"}, {"@otu": "otu216239", "@id": "node509725"}, {"@otu": "otu216223", "@id": "node509726"}], "@about": "#tree1999", "meta": [{"@property": "ot:inGroupClade", "@xsi:type": "nex:LiteralMeta", "$": "node509640"}, {"@property": "ot:tag", "@xsi:type": "nex:LiteralMeta", "$": "ML"}, {"@property": "ot:tag", "@xsi:type": "nex:LiteralMeta", "$": "LSU"}, {"@property": "ot:tag", "@xsi:type": "nex:LiteralMeta", "$": "RPB2"}, {"@property": "ot:tag", "@xsi:type": "nex:LiteralMeta", "$": "EF-1"}, {"@property": "ot:tag", "@xsi:type": "nex:LiteralMeta", "$": "Choose me"}], "edge": [{"@source": "node509636", "@target": "node509637", "@id": "edge509637"}, {"@source": "node509636", "@target": "node509638", "@id": "edge509638"}, {"@source": "node509638", "@target": "node509639", "@id": "edge509639"}, {"@source": "node509638", "@target": "node509640", "@id": "edge509640"}, {"@source": "node509640", "@target": "node509641", "@id": "edge509641"}, {"@source": "node509641", "@target": "node509642", "@id": "edge509642"}, {"@source": "node509642", "@target": "node509643", "@id": "edge509643"}, {"@source": "node509642", "@target": "node509644", "@id": "edge509644"}, {"@source": "node509641", "@target": "node509645", "@id": "edge509645"}, {"@source": "node509645", "@target": "node509646", "@id": "edge509646"}, {"@source": "node509646", "@target": "node509647", "@id": "edge509647"}, {"@source": "node509646", "@target": "node509648", "@id": "edge509648"}, {"@source": "node509648", "@target": "node509649", "@id": "edge509649"}, {"@source": "node509648", "@target": "node509650", "@id": "edge509650"}, {"@source": "node509645", "@target": "node509651", "@id": "edge509651"}, {"@source": "node509651", "@target": "node509652", "@id": "edge509652"}, {"@source": "node509651", "@target": "node509653", "@id": "edge509653"}, {"@source": "node509653", "@target": "node509654", "@id": "edge509654"}, {"@source": "node509653", "@target": "node509655", "@id": "edge509655"}, {"@source": "node509655", "@target": "node509656", "@id": "edge509656"}, {"@source": "node509655", "@target": "node509657", "@id": "edge509657"}, {"@source": "node509657", "@target": "node509658", "@id": "edge509658"}, {"@source": "node509657", "@target": "node509659", "@id": "edge509659"}, {"@source": "node509659", "@target": "node509660", "@id": "edge509660"}, {"@source": "node509659", "@target": "node509661", "@id": "edge509661"}, {"@source": "node509640", "@target": "node509662", "@id": "edge509662"}, {"@source": "node509662", "@target": "node509663", "@id": "edge509663"}, {"@source": "node509663", "@target": "node509664", "@id": "edge509664"}, {"@source": "node509664", "@target": "node509665", "@id": "edge509665"}, {"@source": "node509665", "@target": "node509666", "@id": "edge509666"}, {"@source": "node509666", "@target": "node509667", "@id": "edge509667"}, {"@source": "node509667", "@target": "node509668", "@id": "edge509668"}, {"@source": "node509668", "@target": "node509669", "@id": "edge509669"}, {"@source": "node509669", "@target": "node509670", "@id": "edge509670"}, {"@source": "node509669", "@target": "node509671", "@id": "edge509671"}, {"@source": "node509671", "@target": "node509672", "@id": "edge509672"}, {"@source": "node509671", "@target": "node509673", "@id": "edge509673"}, {"@source": "node509673", "@target": "node509674", "@id": "edge509674"}, {"@source": "node509673", "@target": "node509675", "@id": "edge509675"}, {"@source": "node509668", "@target": "node509676", "@id": "edge509676"}, {"@source": "node509676", "@target": "node509677", "@id": "edge509677"}, {"@source": "node509676", "@target": "node509678", "@id": "edge509678"}, {"@source": "node509667", "@target": "node509679", "@id": "edge509679"}, {"@source": "node509679", "@target": "node509680", "@id": "edge509680"}, {"@source": "node509679", "@target": "node509681", "@id": "edge509681"}, {"@source": "node509681", "@target": "node509682", "@id": "edge509682"}, {"@source": "node509681", "@target": "node509683", "@id": "edge509683"}, {"@source": "node509683", "@target": "node509684", "@id": "edge509684"}, {"@source": "node509683", "@target": "node509685", "@id": "edge509685"}, {"@source": "node509685", "@target": "node509686", "@id": "edge509686"}, {"@source": "node509685", "@target": "node509687", "@id": "edge509687"}, {"@source": "node509666", "@target": "node509688", "@id": "edge509688"}, {"@source": "node509688", "@target": "node509689", "@id": "edge509689"}, {"@source": "node509688", "@target": "node509690", "@id": "edge509690"}, {"@source": "node509665", "@target": "node509691", "@id": "edge509691"}, {"@source": "node509691", "@target": "node509692", "@id": "edge509692"}, {"@source": "node509692", "@target": "node509693", "@id": "edge509693"}, {"@source": "node509692", "@target": "node509694", "@id": "edge509694"}, {"@source": "node509691", "@target": "node509695", "@id": "edge509695"}, {"@source": "node509695", "@target": "node509696", "@id": "edge509696"}, {"@source": "node509695", "@target": "node509697", "@id": "edge509697"}, {"@source": "node509697", "@target": "node509698", "@id": "edge509698"}, {"@source": "node509698", "@target": "node509699", "@id": "edge509699"}, {"@source": "node509698", "@target": "node509700", "@id": "edge509700"}, {"@source": "node509697", "@target": "node509701", "@id": "edge509701"}, {"@source": "node509701", "@target": "node509702", "@id": "edge509702"}, {"@source": "node509701", "@target": "node509703", "@id": "edge509703"}, {"@source": "node509703", "@target": "node509704", "@id": "edge509704"}, {"@source": "node509703", "@target": "node509705", "@id": "edge509705"}, {"@source": "node509664", "@target": "node509706", "@id": "edge509706"}, {"@source": "node509706", "@target": "node509707", "@id": "edge509707"}, {"@source": "node509706", "@target": "node509708", "@id": "edge509708"}, {"@source": "node509708", "@target": "node509709", "@id": "edge509709"}, {"@source": "node509708", "@target": "node509710", "@id": "edge509710"}, {"@source": "node509710", "@target": "node509711", "@id": "edge509711"}, {"@source": "node509710", "@target": "node509712", "@id": "edge509712"}, {"@source": "node509712", "@target": "node509713", "@id": "edge509713"}, {"@source": "node509712", "@target": "node509714", "@id": "edge509714"}, {"@source": "node509663", "@target": "node509715", "@id": "edge509715"}, {"@source": "node509715", "@target": "node509716", "@id": "edge509716"}, {"@source": "node509716", "@target": "node509717", "@id": "edge509717"}, {"@source": "node509716", "@target": "node509718", "@id": "edge509718"}, {"@source": "node509718", "@target": "node509719", "@id": "edge509719"}, {"@source": "node509718", "@target": "node509720", "@id": "edge509720"}, {"@source": "node509715", "@target": "node509721", "@id": "edge509721"}, {"@source": "node509721", "@target": "node509722", "@id": "edge509722"}, {"@source": "node509721", "@target": "node509723", "@id": "edge509723"}, {"@source": "node509662", "@target": "node509724", "@id": "edge509724"}, {"@source": "node509724", "@target": "node509725", "@id": "edge509725"}, {"@source": "node509724", "@target": "node509726", "@id": "edge509726"}], "@id": "tree1999"}]}}}
