{
"nexml": {
"@about": "#study", 
"@generator": "Phylografter nexml-json exporter", 
"@id": "study", 
"@nexmljson": "http://purl.org/opentree/nexson", 
"@version": "0.9", 
"@xmlns": {
"$": "http://www.nexml.org/2009", 
"nex": "http://www.nexml.org/2009", 
"ot": "http://purl.org/opentree-terms#", 
"xsd": "http://www.w3.org/2001/XMLSchema#", 
"xsi": "http://www.w3.org/2001/XMLSchema-instance"
}, 
"meta": [
{
"$": "Kooistra W., Sarno D., Balzano S., Gu H., Andersen R., & Zingone A. 2007. Global diversity and biogeography of Skeletonema species (Bacillariophyta). Protist, null.", 
"@property": "ot:studyPublicationReference", 
"@xsi:type": "nex:LiteralMeta"
}, 
{
"$": "Dail Laughinghouse", 
"@property": "ot:curatorName", 
"@xsi:type": "nex:LiteralMeta"
}, 
{
"@href": "http://purl.org/phylo/treebase/phylows/study/TB2:S1922", 
"@property": "ot:dataDeposit", 
"@xsi:type": "nex:ResourceMeta"
}, 
{
"$": "2774", 
"@property": "ot:studyId", 
"@xsi:type": "nex:LiteralMeta"
}, 
{
"$": 2007, 
"@property": "ot:studyYear", 
"@xsi:type": "nex:LiteralMeta"
}
], 
"otus": {
"@id": "otus2774", 
"otu": [
{
"@about": "#otu412374", 
"@id": "otu412374", 
"@label": "Skeletonema japonicum", 
"meta": [
{
"$": 441575, 
"@property": "ot:ottId", 
"@xsi:type": "nex:LiteralMeta"
}, 
{
"$": "Tl69608", 
"@property": "ot:treebaseOTUId", 
"@xsi:type": "nex:LiteralMeta"
}, 
{
"$": "Skeletonema japonicum HenA6", 
"@property": "ot:originalLabel", 
"@xsi:type": "nex:LiteralMeta"
}
]
}, 
{
"@about": "#otu412375", 
"@id": "otu412375", 
"@label": "Skeletonema marinoi", 
"meta": [
{
"$": 810369, 
"@property": "ot:ottId", 
"@xsi:type": "nex:LiteralMeta"
}, 
{
"$": "Tl69609", 
"@property": "ot:treebaseOTUId", 
"@xsi:type": "nex:LiteralMeta"
}, 
{
"$": "Skeletonema marinoi KAL N2", 
"@property": "ot:originalLabel", 
"@xsi:type": "nex:LiteralMeta"
}
]
}, 
{
"@about": "#otu412376", 
"@id": "otu412376", 
"@label": "Skeletonema dohrnii", 
"meta": [
{
"$": 810367, 
"@property": "ot:ottId", 
"@xsi:type": "nex:LiteralMeta"
}, 
{
"$": "Tl69610", 
"@property": "ot:treebaseOTUId", 
"@xsi:type": "nex:LiteralMeta"
}, 
{
"$": "Skeletonema dohrnii GuHaifeng", 
"@property": "ot:originalLabel", 
"@xsi:type": "nex:LiteralMeta"
}
]
}, 
{
"@about": "#otu412377", 
"@id": "otu412377", 
"@label": "Skeletonema tropicum", 
"meta": [
{
"$": 441574, 
"@property": "ot:ottId", 
"@xsi:type": "nex:LiteralMeta"
}, 
{
"$": "Tl69611", 
"@property": "ot:treebaseOTUId", 
"@xsi:type": "nex:LiteralMeta"
}, 
{
"$": "Skeletonema tropicum SCXM07", 
"@property": "ot:originalLabel", 
"@xsi:type": "nex:LiteralMeta"
}
]
}, 
{
"@about": "#otu412378", 
"@id": "otu412378", 
"@label": "Skeletonema marinoi", 
"meta": [
{
"$": 810369, 
"@property": "ot:ottId", 
"@xsi:type": "nex:LiteralMeta"
}, 
{
"$": "Tl69612", 
"@property": "ot:treebaseOTUId", 
"@xsi:type": "nex:LiteralMeta"
}, 
{
"$": "Skeletonema marinoi AC174", 
"@property": "ot:originalLabel", 
"@xsi:type": "nex:LiteralMeta"
}
]
}, 
{
"@about": "#otu412379", 
"@id": "otu412379", 
"@label": "Skeletonema grethae", 
"meta": [
{
"$": 810365, 
"@property": "ot:ottId", 
"@xsi:type": "nex:LiteralMeta"
}, 
{
"$": "Tl69613", 
"@property": "ot:treebaseOTUId", 
"@xsi:type": "nex:LiteralMeta"
}, 
{
"$": "Skeletonema grethae NOAA D1", 
"@property": "ot:originalLabel", 
"@xsi:type": "nex:LiteralMeta"
}
]
}, 
{
"@about": "#otu412380", 
"@id": "otu412380", 
"@label": "Skeletonema marinoi", 
"meta": [
{
"$": 810369, 
"@property": "ot:ottId", 
"@xsi:type": "nex:LiteralMeta"
}, 
{
"$": "Tl69614", 
"@property": "ot:treebaseOTUId", 
"@xsi:type": "nex:LiteralMeta"
}, 
{
"$": "Skeletonema marinoi CCMP1224", 
"@property": "ot:originalLabel", 
"@xsi:type": "nex:LiteralMeta"
}
]
}, 
{
"@about": "#otu412381", 
"@id": "otu412381", 
"@label": "Skeletonema marinoi", 
"meta": [
{
"$": 810369, 
"@property": "ot:ottId", 
"@xsi:type": "nex:LiteralMeta"
}, 
{
"$": "Tl69615", 
"@property": "ot:treebaseOTUId", 
"@xsi:type": "nex:LiteralMeta"
}, 
{
"$": "Skeletonema marinoi CCMP1223", 
"@property": "ot:originalLabel", 
"@xsi:type": "nex:LiteralMeta"
}
]
}, 
{
"@about": "#otu412382", 
"@id": "otu412382", 
"@label": "Skeletonema marinoi", 
"meta": [
{
"$": 810369, 
"@property": "ot:ottId", 
"@xsi:type": "nex:LiteralMeta"
}, 
{
"$": "Tl69616", 
"@property": "ot:treebaseOTUId", 
"@xsi:type": "nex:LiteralMeta"
}, 
{
"$": "Skeletonema marinoi CCMP1226", 
"@property": "ot:originalLabel", 
"@xsi:type": "nex:LiteralMeta"
}
]
}, 
{
"@about": "#otu412383", 
"@id": "otu412383", 
"@label": "Skeletonema dohrnii", 
"meta": [
{
"$": 810367, 
"@property": "ot:ottId", 
"@xsi:type": "nex:LiteralMeta"
}, 
{
"$": "Tl69617", 
"@property": "ot:treebaseOTUId", 
"@xsi:type": "nex:LiteralMeta"
}, 
{
"$": "Skeletonema dohrnii CCMP782", 
"@property": "ot:originalLabel", 
"@xsi:type": "nex:LiteralMeta"
}
]
}, 
{
"@about": "#otu412384", 
"@id": "otu412384", 
"@label": "Skeletonema marinoi", 
"meta": [
{
"$": 810369, 
"@property": "ot:ottId", 
"@xsi:type": "nex:LiteralMeta"
}, 
{
"$": "Tl69618", 
"@property": "ot:treebaseOTUId", 
"@xsi:type": "nex:LiteralMeta"
}, 
{
"$": "Skeletonema marinoi CAN J1", 
"@property": "ot:originalLabel", 
"@xsi:type": "nex:LiteralMeta"
}
]
}, 
{
"@about": "#otu412385", 
"@id": "otu412385", 
"@label": "Skeletonema tropicum", 
"meta": [
{
"$": 441574, 
"@property": "ot:ottId", 
"@xsi:type": "nex:LiteralMeta"
}, 
{
"$": "Tl69619", 
"@property": "ot:treebaseOTUId", 
"@xsi:type": "nex:LiteralMeta"
}, 
{
"$": "Skeletonema tropicum SK HH", 
"@property": "ot:originalLabel", 
"@xsi:type": "nex:LiteralMeta"
}
]
}, 
{
"@about": "#otu412386", 
"@id": "otu412386", 
"@label": "Skeletonema tropicum", 
"meta": [
{
"$": 441574, 
"@property": "ot:ottId", 
"@xsi:type": "nex:LiteralMeta"
}, 
{
"$": "Tl69620", 
"@property": "ot:treebaseOTUId", 
"@xsi:type": "nex:LiteralMeta"
}, 
{
"$": "Skeletonema tropicum M99", 
"@property": "ot:originalLabel", 
"@xsi:type": "nex:LiteralMeta"
}
]
}, 
{
"@about": "#otu412387", 
"@id": "otu412387", 
"@label": "Skeletonema japonicum", 
"meta": [
{
"$": 441575, 
"@property": "ot:ottId", 
"@xsi:type": "nex:LiteralMeta"
}, 
{
"$": "Tl69621", 
"@property": "ot:treebaseOTUId", 
"@xsi:type": "nex:LiteralMeta"
}, 
{
"$": "Skeletonema japonicum CTCC32", 
"@property": "ot:originalLabel", 
"@xsi:type": "nex:LiteralMeta"
}
]
}, 
{
"@about": "#otu412388", 
"@id": "otu412388", 
"@label": "Skeletonema menzellii", 
"meta": [
{
"$": 322452, 
"@property": "ot:ottId", 
"@xsi:type": "nex:LiteralMeta"
}, 
{
"$": "Tl69622", 
"@property": "ot:treebaseOTUId", 
"@xsi:type": "nex:LiteralMeta"
}, 
{
"$": "Skeletonema menzelii CCMP795", 
"@property": "ot:originalLabel", 
"@xsi:type": "nex:LiteralMeta"
}
]
}, 
{
"@about": "#otu412389", 
"@id": "otu412389", 
"@label": "Skeletonema grethae", 
"meta": [
{
"$": 810365, 
"@property": "ot:ottId", 
"@xsi:type": "nex:LiteralMeta"
}, 
{
"$": "Tl69623", 
"@property": "ot:treebaseOTUId", 
"@xsi:type": "nex:LiteralMeta"
}, 
{
"$": "Skeletonema grethae CCMP780", 
"@property": "ot:originalLabel", 
"@xsi:type": "nex:LiteralMeta"
}
]
}, 
{
"@about": "#otu412390", 
"@id": "otu412390", 
"@label": "Skeletonema tropicum", 
"meta": [
{
"$": 441574, 
"@property": "ot:ottId", 
"@xsi:type": "nex:LiteralMeta"
}, 
{
"$": "Tl69624", 
"@property": "ot:treebaseOTUId", 
"@xsi:type": "nex:LiteralMeta"
}, 
{
"$": "Skeletonema tropicum B142", 
"@property": "ot:originalLabel", 
"@xsi:type": "nex:LiteralMeta"
}
]
}, 
{
"@about": "#otu412391", 
"@id": "otu412391", 
"@label": "Skeletonema pseudocostatum", 
"meta": [
{
"$": 459898, 
"@property": "ot:ottId", 
"@xsi:type": "nex:LiteralMeta"
}, 
{
"$": "Tl69625", 
"@property": "ot:treebaseOTUId", 
"@xsi:type": "nex:LiteralMeta"
}, 
{
"$": "Skeletonema pseudocostatum FKM2", 
"@property": "ot:originalLabel", 
"@xsi:type": "nex:LiteralMeta"
}
]
}, 
{
"@about": "#otu412392", 
"@id": "otu412392", 
"@label": "Skeletonema marinoi", 
"meta": [
{
"$": 810369, 
"@property": "ot:ottId", 
"@xsi:type": "nex:LiteralMeta"
}, 
{
"$": "Tl69626", 
"@property": "ot:treebaseOTUId", 
"@xsi:type": "nex:LiteralMeta"
}, 
{
"$": "Skeletonema marinoi B189hk", 
"@property": "ot:originalLabel", 
"@xsi:type": "nex:LiteralMeta"
}
]
}, 
{
"@about": "#otu412393", 
"@id": "otu412393", 
"@label": "Skeletonema marinoi", 
"meta": [
{
"$": 810369, 
"@property": "ot:ottId", 
"@xsi:type": "nex:LiteralMeta"
}, 
{
"$": "Tl69627", 
"@property": "ot:treebaseOTUId", 
"@xsi:type": "nex:LiteralMeta"
}, 
{
"$": "Skeletonema marinoi KF Y2", 
"@property": "ot:originalLabel", 
"@xsi:type": "nex:LiteralMeta"
}
]
}, 
{
"@about": "#otu412394", 
"@id": "otu412394", 
"@label": "Skeletonema costatum", 
"meta": [
{
"$": 569306, 
"@property": "ot:ottId", 
"@xsi:type": "nex:LiteralMeta"
}, 
{
"$": "Tl69628", 
"@property": "ot:treebaseOTUId", 
"@xsi:type": "nex:LiteralMeta"
}, 
{
"$": "Skeletonema costatum C", 
"@property": "ot:originalLabel", 
"@xsi:type": "nex:LiteralMeta"
}
]
}, 
{
"@about": "#otu412395", 
"@id": "otu412395", 
"@label": "Skeletonema marinoi", 
"meta": [
{
"$": 810369, 
"@property": "ot:ottId", 
"@xsi:type": "nex:LiteralMeta"
}, 
{
"$": "Tl69629", 
"@property": "ot:treebaseOTUId", 
"@xsi:type": "nex:LiteralMeta"
}, 
{
"$": "Skeletonema marinoi AdrN5str10", 
"@property": "ot:originalLabel", 
"@xsi:type": "nex:LiteralMeta"
}
]
}, 
{
"@about": "#otu412396", 
"@id": "otu412396", 
"@label": "Skeletonema dohrnii", 
"meta": [
{
"$": 810367, 
"@property": "ot:ottId", 
"@xsi:type": "nex:LiteralMeta"
}, 
{
"$": "Tl69630", 
"@property": "ot:treebaseOTUId", 
"@xsi:type": "nex:LiteralMeta"
}, 
{
"$": "Skeletonema dohrnii CS408", 
"@property": "ot:originalLabel", 
"@xsi:type": "nex:LiteralMeta"
}
]
}, 
{
"@about": "#otu412397", 
"@id": "otu412397", 
"@label": "Skeletonema menzellii", 
"meta": [
{
"$": 322452, 
"@property": "ot:ottId", 
"@xsi:type": "nex:LiteralMeta"
}, 
{
"$": "Tl69631", 
"@property": "ot:treebaseOTUId", 
"@xsi:type": "nex:LiteralMeta"
}, 
{
"$": "Skeletonema menzelii B138", 
"@property": "ot:originalLabel", 
"@xsi:type": "nex:LiteralMeta"
}
]
}, 
{
"@about": "#otu412398", 
"@id": "otu412398", 
"@label": "Skeletonema grethae", 
"meta": [
{
"$": 810365, 
"@property": "ot:ottId", 
"@xsi:type": "nex:LiteralMeta"
}, 
{
"$": "Tl69632", 
"@property": "ot:treebaseOTUId", 
"@xsi:type": "nex:LiteralMeta"
}, 
{
"$": "Skeletonema grethae CCMP775", 
"@property": "ot:originalLabel", 
"@xsi:type": "nex:LiteralMeta"
}
]
}, 
{
"@about": "#otu412399", 
"@id": "otu412399", 
"@label": "Skeletonema grethae", 
"meta": [
{
"$": 810365, 
"@property": "ot:ottId", 
"@xsi:type": "nex:LiteralMeta"
}, 
{
"$": "Tl69633", 
"@property": "ot:treebaseOTUId", 
"@xsi:type": "nex:LiteralMeta"
}, 
{
"$": "Skeletonema grethae CCAP1077 3", 
"@property": "ot:originalLabel", 
"@xsi:type": "nex:LiteralMeta"
}
]
}, 
{
"@about": "#otu412400", 
"@id": "otu412400", 
"@label": "Skeletonema grevillei", 
"meta": [
{
"$": 777861, 
"@property": "ot:ottId", 
"@xsi:type": "nex:LiteralMeta"
}, 
{
"$": "Tl69634", 
"@property": "ot:treebaseOTUId", 
"@xsi:type": "nex:LiteralMeta"
}, 
{
"$": "Skeletonema grevillei CCMP1685a", 
"@property": "ot:originalLabel", 
"@xsi:type": "nex:LiteralMeta"
}
]
}, 
{
"@about": "#otu412401", 
"@id": "otu412401", 
"@label": "Skeletonema marinoi", 
"meta": [
{
"$": 810369, 
"@property": "ot:ottId", 
"@xsi:type": "nex:LiteralMeta"
}, 
{
"$": "Tl69635", 
"@property": "ot:treebaseOTUId", 
"@xsi:type": "nex:LiteralMeta"
}, 
{
"$": "Skeletonema marinoi CCMP1225", 
"@property": "ot:originalLabel", 
"@xsi:type": "nex:LiteralMeta"
}
]
}, 
{
"@about": "#otu412402", 
"@id": "otu412402", 
"@label": "Skeletonema marinoi", 
"meta": [
{
"$": 810369, 
"@property": "ot:ottId", 
"@xsi:type": "nex:LiteralMeta"
}, 
{
"$": "Tl69636", 
"@property": "ot:treebaseOTUId", 
"@xsi:type": "nex:LiteralMeta"
}, 
{
"$": "Skeletonema marinoi Helgoland", 
"@property": "ot:originalLabel", 
"@xsi:type": "nex:LiteralMeta"
}
]
}, 
{
"@about": "#otu412403", 
"@id": "otu412403", 
"@label": "Skeletonema marinoi", 
"meta": [
{
"$": 810369, 
"@property": "ot:ottId", 
"@xsi:type": "nex:LiteralMeta"
}, 
{
"$": "Tl69637", 
"@property": "ot:treebaseOTUId", 
"@xsi:type": "nex:LiteralMeta"
}, 
{
"$": "Skeletonema marinoi AdrN5str4", 
"@property": "ot:originalLabel", 
"@xsi:type": "nex:LiteralMeta"
}
]
}, 
{
"@about": "#otu412404", 
"@id": "otu412404", 
"@label": "Skeletonema tropicum", 
"meta": [
{
"$": 441574, 
"@property": "ot:ottId", 
"@xsi:type": "nex:LiteralMeta"
}, 
{
"$": "Tl69638", 
"@property": "ot:treebaseOTUId", 
"@xsi:type": "nex:LiteralMeta"
}, 
{
"$": "Skeletonema tropicum MC593", 
"@property": "ot:originalLabel", 
"@xsi:type": "nex:LiteralMeta"
}
]
}, 
{
"@about": "#otu412405", 
"@id": "otu412405", 
"@label": "Skeletonema pseudocostatum", 
"meta": [
{
"$": 459898, 
"@property": "ot:ottId", 
"@xsi:type": "nex:LiteralMeta"
}, 
{
"$": "Tl69639", 
"@property": "ot:treebaseOTUId", 
"@xsi:type": "nex:LiteralMeta"
}, 
{
"$": "Skeletonema pseudocostatum CS25", 
"@property": "ot:originalLabel", 
"@xsi:type": "nex:LiteralMeta"
}
]
}, 
{
"@about": "#otu412406", 
"@id": "otu412406", 
"@label": "Skeletonema tropicum", 
"meta": [
{
"$": 441574, 
"@property": "ot:ottId", 
"@xsi:type": "nex:LiteralMeta"
}, 
{
"$": "Tl69640", 
"@property": "ot:treebaseOTUId", 
"@xsi:type": "nex:LiteralMeta"
}, 
{
"$": "Skeletonema tropicum B214", 
"@property": "ot:originalLabel", 
"@xsi:type": "nex:LiteralMeta"
}
]
}, 
{
"@about": "#otu412407", 
"@id": "otu412407", 
"@label": "Skeletonema marinoi", 
"meta": [
{
"$": 810369, 
"@property": "ot:ottId", 
"@xsi:type": "nex:LiteralMeta"
}, 
{
"$": "Tl69641", 
"@property": "ot:treebaseOTUId", 
"@xsi:type": "nex:LiteralMeta"
}, 
{
"$": "Skeletonema marinoi KF S1", 
"@property": "ot:originalLabel", 
"@xsi:type": "nex:LiteralMeta"
}
]
}, 
{
"@about": "#otu412408", 
"@id": "otu412408", 
"@label": "taxon 212", 
"meta": [
{
"$": "Tl69642", 
"@property": "ot:treebaseOTUId", 
"@xsi:type": "nex:LiteralMeta"
}, 
{
"$": "taxon 212", 
"@property": "ot:originalLabel", 
"@xsi:type": "nex:LiteralMeta"
}
]
}, 
{
"@about": "#otu412409", 
"@id": "otu412409", 
"@label": "Skeletonema grethae", 
"meta": [
{
"$": 810365, 
"@property": "ot:ottId", 
"@xsi:type": "nex:LiteralMeta"
}, 
{
"$": "Tl69643", 
"@property": "ot:treebaseOTUId", 
"@xsi:type": "nex:LiteralMeta"
}, 
{
"$": "Skeletonema grethae NOAA D2", 
"@property": "ot:originalLabel", 
"@xsi:type": "nex:LiteralMeta"
}
]
}, 
{
"@about": "#otu412410", 
"@id": "otu412410", 
"@label": "Skeletonema menzellii", 
"meta": [
{
"$": 322452, 
"@property": "ot:ottId", 
"@xsi:type": "nex:LiteralMeta"
}, 
{
"$": "Tl69644", 
"@property": "ot:treebaseOTUId", 
"@xsi:type": "nex:LiteralMeta"
}, 
{
"$": "Skeletonema menzelii Naos13", 
"@property": "ot:originalLabel", 
"@xsi:type": "nex:LiteralMeta"
}
]
}, 
{
"@about": "#otu412411", 
"@id": "otu412411", 
"@label": "Skeletonema marinoi", 
"meta": [
{
"$": 810369, 
"@property": "ot:ottId", 
"@xsi:type": "nex:LiteralMeta"
}, 
{
"$": "Tl69645", 
"@property": "ot:treebaseOTUId", 
"@xsi:type": "nex:LiteralMeta"
}, 
{
"$": "Skeletonema marinoi AdrN5str1", 
"@property": "ot:originalLabel", 
"@xsi:type": "nex:LiteralMeta"
}
]
}, 
{
"@about": "#otu412412", 
"@id": "otu412412", 
"@label": "Skeletonema dohrnii", 
"meta": [
{
"$": 810367, 
"@property": "ot:ottId", 
"@xsi:type": "nex:LiteralMeta"
}, 
{
"$": "Tl69646", 
"@property": "ot:treebaseOTUId", 
"@xsi:type": "nex:LiteralMeta"
}, 
{
"$": "Skeletonema dohrnii NIES223", 
"@property": "ot:originalLabel", 
"@xsi:type": "nex:LiteralMeta"
}
]
}, 
{
"@about": "#otu412413", 
"@id": "otu412413", 
"@label": "Skeletonema grethae", 
"meta": [
{
"$": 810365, 
"@property": "ot:ottId", 
"@xsi:type": "nex:LiteralMeta"
}, 
{
"$": "Tl69647", 
"@property": "ot:treebaseOTUId", 
"@xsi:type": "nex:LiteralMeta"
}, 
{
"$": "Skeletonema grethae NOAA C1", 
"@property": "ot:originalLabel", 
"@xsi:type": "nex:LiteralMeta"
}
]
}, 
{
"@about": "#otu412414", 
"@id": "otu412414", 
"@label": "Skeletonema marinoi", 
"meta": [
{
"$": 810369, 
"@property": "ot:ottId", 
"@xsi:type": "nex:LiteralMeta"
}, 
{
"$": "Tl69648", 
"@property": "ot:treebaseOTUId", 
"@xsi:type": "nex:LiteralMeta"
}, 
{
"$": "Skeletonema marinoi CAN G1", 
"@property": "ot:originalLabel", 
"@xsi:type": "nex:LiteralMeta"
}
]
}, 
{
"@about": "#otu412415", 
"@id": "otu412415", 
"@label": "Skeletonema marinoi", 
"meta": [
{
"$": 810369, 
"@property": "ot:ottId", 
"@xsi:type": "nex:LiteralMeta"
}, 
{
"$": "Tl69649", 
"@property": "ot:treebaseOTUId", 
"@xsi:type": "nex:LiteralMeta"
}, 
{
"$": "Skeletonema marinoi AdrN5str9", 
"@property": "ot:originalLabel", 
"@xsi:type": "nex:LiteralMeta"
}
]
}, 
{
"@about": "#otu412416", 
"@id": "otu412416", 
"@label": "Skeletonema ardens", 
"meta": [
{
"$": 777867, 
"@property": "ot:ottId", 
"@xsi:type": "nex:LiteralMeta"
}, 
{
"$": "Tl69650", 
"@property": "ot:treebaseOTUId", 
"@xsi:type": "nex:LiteralMeta"
}, 
{
"$": "Skeletonema ardens CS348", 
"@property": "ot:originalLabel", 
"@xsi:type": "nex:LiteralMeta"
}
]
}, 
{
"@about": "#otu412417", 
"@id": "otu412417", 
"@label": "Skeletonema marinoi", 
"meta": [
{
"$": 810369, 
"@property": "ot:ottId", 
"@xsi:type": "nex:LiteralMeta"
}, 
{
"$": "Tl69651", 
"@property": "ot:treebaseOTUId", 
"@xsi:type": "nex:LiteralMeta"
}, 
{
"$": "Skeletonema marinoi PORT C3", 
"@property": "ot:originalLabel", 
"@xsi:type": "nex:LiteralMeta"
}
]
}, 
{
"@about": "#otu412418", 
"@id": "otu412418", 
"@label": "Skeletonema marinoi", 
"meta": [
{
"$": 810369, 
"@property": "ot:ottId", 
"@xsi:type": "nex:LiteralMeta"
}, 
{
"$": "Tl69652", 
"@property": "ot:treebaseOTUId", 
"@xsi:type": "nex:LiteralMeta"
}, 
{
"$": "Skeletonema marinoi PORT G3", 
"@property": "ot:originalLabel", 
"@xsi:type": "nex:LiteralMeta"
}
]
}, 
{
"@about": "#otu412419", 
"@id": "otu412419", 
"@label": "Skeletonema menzellii", 
"meta": [
{
"$": 322452, 
"@property": "ot:ottId", 
"@xsi:type": "nex:LiteralMeta"
}, 
{
"$": "Tl69653", 
"@property": "ot:treebaseOTUId", 
"@xsi:type": "nex:LiteralMeta"
}, 
{
"$": "Skeletonema menzelii NORBAL", 
"@property": "ot:originalLabel", 
"@xsi:type": "nex:LiteralMeta"
}
]
}, 
{
"@about": "#otu412420", 
"@id": "otu412420", 
"@label": "Skeletonema grethae", 
"meta": [
{
"$": 810365, 
"@property": "ot:ottId", 
"@xsi:type": "nex:LiteralMeta"
}, 
{
"$": "Tl69654", 
"@property": "ot:treebaseOTUId", 
"@xsi:type": "nex:LiteralMeta"
}, 
{
"$": "Skeletonema grethae NOAA B1", 
"@property": "ot:originalLabel", 
"@xsi:type": "nex:LiteralMeta"
}
]
}, 
{
"@about": "#otu412421", 
"@id": "otu412421", 
"@label": "Skeletonema japonicum", 
"meta": [
{
"$": 441575, 
"@property": "ot:ottId", 
"@xsi:type": "nex:LiteralMeta"
}, 
{
"$": "Tl69655", 
"@property": "ot:treebaseOTUId", 
"@xsi:type": "nex:LiteralMeta"
}, 
{
"$": "Skeletonema japonicum Nar3", 
"@property": "ot:originalLabel", 
"@xsi:type": "nex:LiteralMeta"
}
]
}, 
{
"@about": "#otu412422", 
"@id": "otu412422", 
"@label": "Skeletonema dohrnii", 
"meta": [
{
"$": 810367, 
"@property": "ot:ottId", 
"@xsi:type": "nex:LiteralMeta"
}, 
{
"$": "Tl69656", 
"@property": "ot:treebaseOTUId", 
"@xsi:type": "nex:LiteralMeta"
}, 
{
"$": "Skeletonema dohrnii NIES324", 
"@property": "ot:originalLabel", 
"@xsi:type": "nex:LiteralMeta"
}
]
}, 
{
"@about": "#otu412423", 
"@id": "otu412423", 
"@label": "Skeletonema marinoi", 
"meta": [
{
"$": 810369, 
"@property": "ot:ottId", 
"@xsi:type": "nex:LiteralMeta"
}, 
{
"$": "Tl69657", 
"@property": "ot:treebaseOTUId", 
"@xsi:type": "nex:LiteralMeta"
}, 
{
"$": "Skeletonema marinoi RCSKB2r", 
"@property": "ot:originalLabel", 
"@xsi:type": "nex:LiteralMeta"
}
]
}, 
{
"@about": "#otu412424", 
"@id": "otu412424", 
"@label": "Skeletonema grethae", 
"meta": [
{
"$": 810365, 
"@property": "ot:ottId", 
"@xsi:type": "nex:LiteralMeta"
}, 
{
"$": "Tl69658", 
"@property": "ot:treebaseOTUId", 
"@xsi:type": "nex:LiteralMeta"
}, 
{
"$": "Skeletonema grethae B194", 
"@property": "ot:originalLabel", 
"@xsi:type": "nex:LiteralMeta"
}
]
}, 
{
"@about": "#otu412425", 
"@id": "otu412425", 
"@label": "Skeletonema marinoi", 
"meta": [
{
"$": 810369, 
"@property": "ot:ottId", 
"@xsi:type": "nex:LiteralMeta"
}, 
{
"$": "Tl69659", 
"@property": "ot:treebaseOTUId", 
"@xsi:type": "nex:LiteralMeta"
}, 
{
"$": "Skeletonema marinoi NorwayG", 
"@property": "ot:originalLabel", 
"@xsi:type": "nex:LiteralMeta"
}
]
}, 
{
"@about": "#otu412426", 
"@id": "otu412426", 
"@label": "Skeletonema marinoi", 
"meta": [
{
"$": 810369, 
"@property": "ot:ottId", 
"@xsi:type": "nex:LiteralMeta"
}, 
{
"$": "Tl69660", 
"@property": "ot:treebaseOTUId", 
"@xsi:type": "nex:LiteralMeta"
}, 
{
"$": "Skeletonema marinoi AdrN5str5", 
"@property": "ot:originalLabel", 
"@xsi:type": "nex:LiteralMeta"
}
]
}, 
{
"@about": "#otu412427", 
"@id": "otu412427", 
"@label": "Skeletonema tropicum", 
"meta": [
{
"$": 441574, 
"@property": "ot:ottId", 
"@xsi:type": "nex:LiteralMeta"
}, 
{
"$": "Tl69661", 
"@property": "ot:treebaseOTUId", 
"@xsi:type": "nex:LiteralMeta"
}, 
{
"$": "Skeletonema tropicum B145", 
"@property": "ot:originalLabel", 
"@xsi:type": "nex:LiteralMeta"
}
]
}, 
{
"@about": "#otu412428", 
"@id": "otu412428", 
"@label": "Skeletonema grevillei", 
"meta": [
{
"$": 777861, 
"@property": "ot:ottId", 
"@xsi:type": "nex:LiteralMeta"
}, 
{
"$": "Tl69662", 
"@property": "ot:treebaseOTUId", 
"@xsi:type": "nex:LiteralMeta"
}, 
{
"$": "Skeletonema grevillei SCX09Xiam", 
"@property": "ot:originalLabel", 
"@xsi:type": "nex:LiteralMeta"
}
]
}, 
{
"@about": "#otu412429", 
"@id": "otu412429", 
"@label": "Skeletonema marinoi", 
"meta": [
{
"$": 810369, 
"@property": "ot:ottId", 
"@xsi:type": "nex:LiteralMeta"
}, 
{
"$": "Tl69663", 
"@property": "ot:treebaseOTUId", 
"@xsi:type": "nex:LiteralMeta"
}, 
{
"$": "Skeletonema marinoi AdrN5str6", 
"@property": "ot:originalLabel", 
"@xsi:type": "nex:LiteralMeta"
}
]
}, 
{
"@about": "#otu412430", 
"@id": "otu412430", 
"@label": "Skeletonema grethae", 
"meta": [
{
"$": 810365, 
"@property": "ot:ottId", 
"@xsi:type": "nex:LiteralMeta"
}, 
{
"$": "Tl69664", 
"@property": "ot:treebaseOTUId", 
"@xsi:type": "nex:LiteralMeta"
}, 
{
"$": "Skeletonema grethae NOAA B2", 
"@property": "ot:originalLabel", 
"@xsi:type": "nex:LiteralMeta"
}
]
}, 
{
"@about": "#otu412431", 
"@id": "otu412431", 
"@label": "Skeletonema marinoi", 
"meta": [
{
"$": 810369, 
"@property": "ot:ottId", 
"@xsi:type": "nex:LiteralMeta"
}, 
{
"$": "Tl69665", 
"@property": "ot:treebaseOTUId", 
"@xsi:type": "nex:LiteralMeta"
}, 
{
"$": "Skeletonema marinoi PORT D2", 
"@property": "ot:originalLabel", 
"@xsi:type": "nex:LiteralMeta"
}
]
}, 
{
"@about": "#otu412432", 
"@id": "otu412432", 
"@label": "Skeletonema dohrnii", 
"meta": [
{
"$": 810367, 
"@property": "ot:ottId", 
"@xsi:type": "nex:LiteralMeta"
}, 
{
"$": "Tl69666", 
"@property": "ot:treebaseOTUId", 
"@xsi:type": "nex:LiteralMeta"
}, 
{
"$": "Skeletonema dohrnii SK BH", 
"@property": "ot:originalLabel", 
"@xsi:type": "nex:LiteralMeta"
}
]
}, 
{
"@about": "#otu412433", 
"@id": "otu412433", 
"@label": "Skeletonema marinoi", 
"meta": [
{
"$": 810369, 
"@property": "ot:ottId", 
"@xsi:type": "nex:LiteralMeta"
}, 
{
"$": "Tl69667", 
"@property": "ot:treebaseOTUId", 
"@xsi:type": "nex:LiteralMeta"
}, 
{
"$": "Skeletonema marinoi NorwayH", 
"@property": "ot:originalLabel", 
"@xsi:type": "nex:LiteralMeta"
}
]
}, 
{
"@about": "#otu412434", 
"@id": "otu412434", 
"@label": "Skeletonema grethae", 
"meta": [
{
"$": 810365, 
"@property": "ot:ottId", 
"@xsi:type": "nex:LiteralMeta"
}, 
{
"$": "Tl69668", 
"@property": "ot:treebaseOTUId", 
"@xsi:type": "nex:LiteralMeta"
}, 
{
"$": "Skeletonema grethae CCMP1804", 
"@property": "ot:originalLabel", 
"@xsi:type": "nex:LiteralMeta"
}
]
}, 
{
"@about": "#otu412435", 
"@id": "otu412435", 
"@label": "Skeletonema dohrnii", 
"meta": [
{
"$": 810367, 
"@property": "ot:ottId", 
"@xsi:type": "nex:LiteralMeta"
}, 
{
"$": "Tl69669", 
"@property": "ot:treebaseOTUId", 
"@xsi:type": "nex:LiteralMeta"
}, 
{
"$": "Skeletonema dohrnii PLY612", 
"@property": "ot:originalLabel", 
"@xsi:type": "nex:LiteralMeta"
}
]
}, 
{
"@about": "#otu412436", 
"@id": "otu412436", 
"@label": "Skeletonema marinoi", 
"meta": [
{
"$": 810369, 
"@property": "ot:ottId", 
"@xsi:type": "nex:LiteralMeta"
}, 
{
"$": "Tl69670", 
"@property": "ot:treebaseOTUId", 
"@xsi:type": "nex:LiteralMeta"
}, 
{
"$": "Skeletonema marinoi KAL E1", 
"@property": "ot:originalLabel", 
"@xsi:type": "nex:LiteralMeta"
}
]
}, 
{
"@about": "#otu412437", 
"@id": "otu412437", 
"@label": "Skeletonema tropicum", 
"meta": [
{
"$": 441574, 
"@property": "ot:ottId", 
"@xsi:type": "nex:LiteralMeta"
}, 
{
"$": "Tl69671", 
"@property": "ot:treebaseOTUId", 
"@xsi:type": "nex:LiteralMeta"
}, 
{
"$": "Skeletonema tropicum B144", 
"@property": "ot:originalLabel", 
"@xsi:type": "nex:LiteralMeta"
}
]
}, 
{
"@about": "#otu412438", 
"@id": "otu412438", 
"@label": "Skeletonema tropicum", 
"meta": [
{
"$": 441574, 
"@property": "ot:ottId", 
"@xsi:type": "nex:LiteralMeta"
}, 
{
"$": "Tl69672", 
"@property": "ot:treebaseOTUId", 
"@xsi:type": "nex:LiteralMeta"
}, 
{
"$": "Skeletonema tropicum B143", 
"@property": "ot:originalLabel", 
"@xsi:type": "nex:LiteralMeta"
}
]
}, 
{
"@about": "#otu412439", 
"@id": "otu412439", 
"@label": "Skeletonema pseudocostatum", 
"meta": [
{
"$": 459898, 
"@property": "ot:ottId", 
"@xsi:type": "nex:LiteralMeta"
}, 
{
"$": "Tl69673", 
"@property": "ot:treebaseOTUId", 
"@xsi:type": "nex:LiteralMeta"
}, 
{
"$": "Skeletonema cf pseudocostatum", 
"@property": "ot:originalLabel", 
"@xsi:type": "nex:LiteralMeta"
}
]
}, 
{
"@about": "#otu412440", 
"@id": "otu412440", 
"@label": "Skeletonema marinoi", 
"meta": [
{
"$": 810369, 
"@property": "ot:ottId", 
"@xsi:type": "nex:LiteralMeta"
}, 
{
"$": "Tl69674", 
"@property": "ot:treebaseOTUId", 
"@xsi:type": "nex:LiteralMeta"
}, 
{
"$": "Skeletonema marinoi CAN D2", 
"@property": "ot:originalLabel", 
"@xsi:type": "nex:LiteralMeta"
}
]
}, 
{
"@about": "#otu412441", 
"@id": "otu412441", 
"@label": "Skeletonema tropicum", 
"meta": [
{
"$": 441574, 
"@property": "ot:ottId", 
"@xsi:type": "nex:LiteralMeta"
}, 
{
"$": "Tl69675", 
"@property": "ot:treebaseOTUId", 
"@xsi:type": "nex:LiteralMeta"
}, 
{
"$": "Skeletonema tropicum SCND03", 
"@property": "ot:originalLabel", 
"@xsi:type": "nex:LiteralMeta"
}
]
}, 
{
"@about": "#otu412442", 
"@id": "otu412442", 
"@label": "Skeletonema pseudocostatum", 
"meta": [
{
"$": 459898, 
"@property": "ot:ottId", 
"@xsi:type": "nex:LiteralMeta"
}, 
{
"$": "Tl69676", 
"@property": "ot:treebaseOTUId", 
"@xsi:type": "nex:LiteralMeta"
}, 
{
"$": "Skeletonema pseudocostatum CCAP", 
"@property": "ot:originalLabel", 
"@xsi:type": "nex:LiteralMeta"
}
]
}, 
{
"@about": "#otu412443", 
"@id": "otu412443", 
"@label": "Skeletonema marinoi", 
"meta": [
{
"$": 810369, 
"@property": "ot:ottId", 
"@xsi:type": "nex:LiteralMeta"
}, 
{
"$": "Tl69677", 
"@property": "ot:treebaseOTUId", 
"@xsi:type": "nex:LiteralMeta"
}, 
{
"$": "Skeletonema marinoi AdrN5str8", 
"@property": "ot:originalLabel", 
"@xsi:type": "nex:LiteralMeta"
}
]
}, 
{
"@about": "#otu412444", 
"@id": "otu412444", 
"@label": "Skeletonema marinoi", 
"meta": [
{
"$": 810369, 
"@property": "ot:ottId", 
"@xsi:type": "nex:LiteralMeta"
}, 
{
"$": "Tl69678", 
"@property": "ot:treebaseOTUId", 
"@xsi:type": "nex:LiteralMeta"
}, 
{
"$": "Skeletonema marinoi PLY106", 
"@property": "ot:originalLabel", 
"@xsi:type": "nex:LiteralMeta"
}
]
}, 
{
"@about": "#otu412445", 
"@id": "otu412445", 
"@label": "Skeletonema pseudocostatum", 
"meta": [
{
"$": 459898, 
"@property": "ot:ottId", 
"@xsi:type": "nex:LiteralMeta"
}, 
{
"$": "Tl69679", 
"@property": "ot:treebaseOTUId", 
"@xsi:type": "nex:LiteralMeta"
}, 
{
"$": "Skeletonema pseudocostatum CLA1", 
"@property": "ot:originalLabel", 
"@xsi:type": "nex:LiteralMeta"
}
]
}, 
{
"@about": "#otu412446", 
"@id": "otu412446", 
"@label": "Skeletonema marinoi", 
"meta": [
{
"$": 810369, 
"@property": "ot:ottId", 
"@xsi:type": "nex:LiteralMeta"
}, 
{
"$": "Tl69680", 
"@property": "ot:treebaseOTUId", 
"@xsi:type": "nex:LiteralMeta"
}, 
{
"$": "Skeletonema marinoi B217", 
"@property": "ot:originalLabel", 
"@xsi:type": "nex:LiteralMeta"
}
]
}, 
{
"@about": "#otu412447", 
"@id": "otu412447", 
"@label": "Skeletonema grethae", 
"meta": [
{
"$": 810365, 
"@property": "ot:ottId", 
"@xsi:type": "nex:LiteralMeta"
}, 
{
"$": "Tl69681", 
"@property": "ot:treebaseOTUId", 
"@xsi:type": "nex:LiteralMeta"
}, 
{
"$": "Skeletonema grethae B195", 
"@property": "ot:originalLabel", 
"@xsi:type": "nex:LiteralMeta"
}
]
}, 
{
"@about": "#otu412448", 
"@id": "otu412448", 
"@label": "Skeletonema ardens", 
"meta": [
{
"$": 777867, 
"@property": "ot:ottId", 
"@xsi:type": "nex:LiteralMeta"
}, 
{
"$": "Tl69682", 
"@property": "ot:treebaseOTUId", 
"@xsi:type": "nex:LiteralMeta"
}, 
{
"$": "Skeletonema ardens SCXM13", 
"@property": "ot:originalLabel", 
"@xsi:type": "nex:LiteralMeta"
}
]
}, 
{
"@about": "#otu412449", 
"@id": "otu412449", 
"@label": "Skeletonema marinoi", 
"meta": [
{
"$": 810369, 
"@property": "ot:ottId", 
"@xsi:type": "nex:LiteralMeta"
}, 
{
"$": "Tl69683", 
"@property": "ot:treebaseOTUId", 
"@xsi:type": "nex:LiteralMeta"
}, 
{
"$": "Skeletonema marinoi B218", 
"@property": "ot:originalLabel", 
"@xsi:type": "nex:LiteralMeta"
}
]
}, 
{
"@about": "#otu412450", 
"@id": "otu412450", 
"@label": "Skeletonema dohrnii", 
"meta": [
{
"$": 810367, 
"@property": "ot:ottId", 
"@xsi:type": "nex:LiteralMeta"
}, 
{
"$": "Tl69684", 
"@property": "ot:treebaseOTUId", 
"@xsi:type": "nex:LiteralMeta"
}, 
{
"$": "Skeletonema dohrnii NIES323", 
"@property": "ot:originalLabel", 
"@xsi:type": "nex:LiteralMeta"
}
]
}, 
{
"@about": "#otu412451", 
"@id": "otu412451", 
"@label": "Skeletonema marinoi", 
"meta": [
{
"$": 810369, 
"@property": "ot:ottId", 
"@xsi:type": "nex:LiteralMeta"
}, 
{
"$": "Tl69685", 
"@property": "ot:treebaseOTUId", 
"@xsi:type": "nex:LiteralMeta"
}, 
{
"$": "Skeletonema marinoi AC623", 
"@property": "ot:originalLabel", 
"@xsi:type": "nex:LiteralMeta"
}
]
}, 
{
"@about": "#otu412452", 
"@id": "otu412452", 
"@label": "Skeletonema marinoi", 
"meta": [
{
"$": 810369, 
"@property": "ot:ottId", 
"@xsi:type": "nex:LiteralMeta"
}, 
{
"$": "Tl69686", 
"@property": "ot:treebaseOTUId", 
"@xsi:type": "nex:LiteralMeta"
}, 
{
"$": "Skeletonema marinoi FE46", 
"@property": "ot:originalLabel", 
"@xsi:type": "nex:LiteralMeta"
}
]
}, 
{
"@about": "#otu412453", 
"@id": "otu412453", 
"@label": "Skeletonema marinoi", 
"meta": [
{
"$": 810369, 
"@property": "ot:ottId", 
"@xsi:type": "nex:LiteralMeta"
}, 
{
"$": "Tl69687", 
"@property": "ot:treebaseOTUId", 
"@xsi:type": "nex:LiteralMeta"
}, 
{
"$": "Skeletonema marinoi KF R2", 
"@property": "ot:originalLabel", 
"@xsi:type": "nex:LiteralMeta"
}
]
}, 
{
"@about": "#otu412454", 
"@id": "otu412454", 
"@label": "Skeletonema marinoi", 
"meta": [
{
"$": 810369, 
"@property": "ot:ottId", 
"@xsi:type": "nex:LiteralMeta"
}, 
{
"$": "Tl69688", 
"@property": "ot:treebaseOTUId", 
"@xsi:type": "nex:LiteralMeta"
}, 
{
"$": "Skeletonema marinoi KF L3", 
"@property": "ot:originalLabel", 
"@xsi:type": "nex:LiteralMeta"
}
]
}, 
{
"@about": "#otu412455", 
"@id": "otu412455", 
"@label": "Skeletonema menzellii", 
"meta": [
{
"$": 322452, 
"@property": "ot:ottId", 
"@xsi:type": "nex:LiteralMeta"
}, 
{
"$": "Tl69689", 
"@property": "ot:treebaseOTUId", 
"@xsi:type": "nex:LiteralMeta"
}, 
{
"$": "Skeletonema menzelii CCMP793", 
"@property": "ot:originalLabel", 
"@xsi:type": "nex:LiteralMeta"
}
]
}, 
{
"@about": "#otu412456", 
"@id": "otu412456", 
"@label": "Skeletonema dohrnii", 
"meta": [
{
"$": 810367, 
"@property": "ot:ottId", 
"@xsi:type": "nex:LiteralMeta"
}, 
{
"$": "Tl69690", 
"@property": "ot:treebaseOTUId", 
"@xsi:type": "nex:LiteralMeta"
}, 
{
"$": "Skeletonema dohrnii NIES16", 
"@property": "ot:originalLabel", 
"@xsi:type": "nex:LiteralMeta"
}
]
}, 
{
"@about": "#otu412457", 
"@id": "otu412457", 
"@label": "Skeletonema marinoi", 
"meta": [
{
"$": 810369, 
"@property": "ot:ottId", 
"@xsi:type": "nex:LiteralMeta"
}, 
{
"$": "Tl69691", 
"@property": "ot:treebaseOTUId", 
"@xsi:type": "nex:LiteralMeta"
}, 
{
"$": "Skeletonema marinoi RCSKB1", 
"@property": "ot:originalLabel", 
"@xsi:type": "nex:LiteralMeta"
}
]
}, 
{
"@about": "#otu412458", 
"@id": "otu412458", 
"@label": "Skeletonema marinoi", 
"meta": [
{
"$": 810369, 
"@property": "ot:ottId", 
"@xsi:type": "nex:LiteralMeta"
}, 
{
"$": "Tl69692", 
"@property": "ot:treebaseOTUId", 
"@xsi:type": "nex:LiteralMeta"
}, 
{
"$": "Skeletonema marinoi B147", 
"@property": "ot:originalLabel", 
"@xsi:type": "nex:LiteralMeta"
}
]
}, 
{
"@about": "#otu412459", 
"@id": "otu412459", 
"@label": "Skeletonema pseudocostatum", 
"meta": [
{
"$": 459898, 
"@property": "ot:ottId", 
"@xsi:type": "nex:LiteralMeta"
}, 
{
"$": "Tl69693", 
"@property": "ot:treebaseOTUId", 
"@xsi:type": "nex:LiteralMeta"
}, 
{
"$": "Skeletonema pseudocostatum Y115", 
"@property": "ot:originalLabel", 
"@xsi:type": "nex:LiteralMeta"
}
]
}, 
{
"@about": "#otu412460", 
"@id": "otu412460", 
"@label": "Skeletonema tropicum", 
"meta": [
{
"$": 441574, 
"@property": "ot:ottId", 
"@xsi:type": "nex:LiteralMeta"
}, 
{
"$": "Tl69694", 
"@property": "ot:treebaseOTUId", 
"@xsi:type": "nex:LiteralMeta"
}, 
{
"$": "Skeletonema tropicum B208", 
"@property": "ot:originalLabel", 
"@xsi:type": "nex:LiteralMeta"
}
]
}, 
{
"@about": "#otu412461", 
"@id": "otu412461", 
"@label": "Skeletonema japonicum", 
"meta": [
{
"$": 441575, 
"@property": "ot:ottId", 
"@xsi:type": "nex:LiteralMeta"
}, 
{
"$": "Tl69695", 
"@property": "ot:treebaseOTUId", 
"@xsi:type": "nex:LiteralMeta"
}, 
{
"$": "Skeletonema japonicum chile", 
"@property": "ot:originalLabel", 
"@xsi:type": "nex:LiteralMeta"
}
]
}, 
{
"@about": "#otu412462", 
"@id": "otu412462", 
"@label": "Skeletonema menzellii", 
"meta": [
{
"$": 322452, 
"@property": "ot:ottId", 
"@xsi:type": "nex:LiteralMeta"
}, 
{
"$": "Tl69696", 
"@property": "ot:treebaseOTUId", 
"@xsi:type": "nex:LiteralMeta"
}, 
{
"$": "Skeletonema menzelii CCMP790", 
"@property": "ot:originalLabel", 
"@xsi:type": "nex:LiteralMeta"
}
]
}, 
{
"@about": "#otu412463", 
"@id": "otu412463", 
"@label": "Skeletonema tropicum", 
"meta": [
{
"$": 441574, 
"@property": "ot:ottId", 
"@xsi:type": "nex:LiteralMeta"
}, 
{
"$": "Tl69697", 
"@property": "ot:treebaseOTUId", 
"@xsi:type": "nex:LiteralMeta"
}, 
{
"$": "Skeletonema tropicum B164", 
"@property": "ot:originalLabel", 
"@xsi:type": "nex:LiteralMeta"
}
]
}, 
{
"@about": "#otu412464", 
"@id": "otu412464", 
"@label": "Skeletonema marinoi", 
"meta": [
{
"$": 810369, 
"@property": "ot:ottId", 
"@xsi:type": "nex:LiteralMeta"
}, 
{
"$": "Tl69698", 
"@property": "ot:treebaseOTUId", 
"@xsi:type": "nex:LiteralMeta"
}, 
{
"$": "Skeletonema marinoi 14A4", 
"@property": "ot:originalLabel", 
"@xsi:type": "nex:LiteralMeta"
}
]
}, 
{
"@about": "#otu412465", 
"@id": "otu412465", 
"@label": "Skeletonema grethae", 
"meta": [
{
"$": 810365, 
"@property": "ot:ottId", 
"@xsi:type": "nex:LiteralMeta"
}, 
{
"$": "Tl69699", 
"@property": "ot:treebaseOTUId", 
"@xsi:type": "nex:LiteralMeta"
}, 
{
"$": "Skeletonema grethae B199", 
"@property": "ot:originalLabel", 
"@xsi:type": "nex:LiteralMeta"
}
]
}, 
{
"@about": "#otu412466", 
"@id": "otu412466", 
"@label": "Skeletonema menzellii", 
"meta": [
{
"$": 322452, 
"@property": "ot:ottId", 
"@xsi:type": "nex:LiteralMeta"
}, 
{
"$": "Tl69700", 
"@property": "ot:treebaseOTUId", 
"@xsi:type": "nex:LiteralMeta"
}, 
{
"$": "Skeletonema menzelii CCMP792", 
"@property": "ot:originalLabel", 
"@xsi:type": "nex:LiteralMeta"
}
]
}, 
{
"@about": "#otu412467", 
"@id": "otu412467", 
"@label": "Skeletonema tropicum", 
"meta": [
{
"$": 441574, 
"@property": "ot:ottId", 
"@xsi:type": "nex:LiteralMeta"
}, 
{
"$": "Tl69701", 
"@property": "ot:treebaseOTUId", 
"@xsi:type": "nex:LiteralMeta"
}, 
{
"$": "Skeletonema tropicum CCMP788", 
"@property": "ot:originalLabel", 
"@xsi:type": "nex:LiteralMeta"
}
]
}, 
{
"@about": "#otu412468", 
"@id": "otu412468", 
"@label": "Skeletonema marinoi", 
"meta": [
{
"$": 810369, 
"@property": "ot:ottId", 
"@xsi:type": "nex:LiteralMeta"
}, 
{
"$": "Tl69702", 
"@property": "ot:treebaseOTUId", 
"@xsi:type": "nex:LiteralMeta"
}, 
{
"$": "Skeletonema marinoi AdrN5str7", 
"@property": "ot:originalLabel", 
"@xsi:type": "nex:LiteralMeta"
}
]
}, 
{
"@about": "#otu412469", 
"@id": "otu412469", 
"@label": "Skeletonema pseudocostatum", 
"meta": [
{
"$": 459898, 
"@property": "ot:ottId", 
"@xsi:type": "nex:LiteralMeta"
}, 
{
"$": "Tl69703", 
"@property": "ot:treebaseOTUId", 
"@xsi:type": "nex:LiteralMeta"
}, 
{
"$": "Skeletonema pseudocostatum CS16", 
"@property": "ot:originalLabel", 
"@xsi:type": "nex:LiteralMeta"
}
]
}, 
{
"@about": "#otu412470", 
"@id": "otu412470", 
"@label": "Skeletonema pseudocostatum", 
"meta": [
{
"$": 459898, 
"@property": "ot:ottId", 
"@xsi:type": "nex:LiteralMeta"
}, 
{
"$": "Tl69704", 
"@property": "ot:treebaseOTUId", 
"@xsi:type": "nex:LiteralMeta"
}, 
{
"$": "Skeletonema pseudocostatum B78", 
"@property": "ot:originalLabel", 
"@xsi:type": "nex:LiteralMeta"
}
]
}, 
{
"@about": "#otu412471", 
"@id": "otu412471", 
"@label": "Cyclotella meneghiniana", 
"meta": [
{
"$": 422808, 
"@property": "ot:ottId", 
"@xsi:type": "nex:LiteralMeta"
}, 
{
"$": "Tl69705", 
"@property": "ot:treebaseOTUId", 
"@xsi:type": "nex:LiteralMeta"
}, 
{
"$": "Cyclotella meneghiniana", 
"@property": "ot:originalLabel", 
"@xsi:type": "nex:LiteralMeta"
}
]
}, 
{
"@about": "#otu412472", 
"@id": "otu412472", 
"@label": "Skeletonema dohrnii", 
"meta": [
{
"$": 810367, 
"@property": "ot:ottId", 
"@xsi:type": "nex:LiteralMeta"
}, 
{
"$": "Tl69706", 
"@property": "ot:treebaseOTUId", 
"@xsi:type": "nex:LiteralMeta"
}, 
{
"$": "Skeletonema dohrnii B105", 
"@property": "ot:originalLabel", 
"@xsi:type": "nex:LiteralMeta"
}
]
}, 
{
"@about": "#otu412473", 
"@id": "otu412473", 
"@label": "Skeletonema japonicum", 
"meta": [
{
"$": 441575, 
"@property": "ot:ottId", 
"@xsi:type": "nex:LiteralMeta"
}, 
{
"$": "Tl69707", 
"@property": "ot:treebaseOTUId", 
"@xsi:type": "nex:LiteralMeta"
}, 
{
"$": "Skeletonema japonicum B149", 
"@property": "ot:originalLabel", 
"@xsi:type": "nex:LiteralMeta"
}
]
}, 
{
"@about": "#otu412474", 
"@id": "otu412474", 
"@label": "Skeletonema pseudocostatum", 
"meta": [
{
"$": 459898, 
"@property": "ot:ottId", 
"@xsi:type": "nex:LiteralMeta"
}, 
{
"$": "Tl69708", 
"@property": "ot:treebaseOTUId", 
"@xsi:type": "nex:LiteralMeta"
}, 
{
"$": "Skeletonema pseudocostatum B140", 
"@property": "ot:originalLabel", 
"@xsi:type": "nex:LiteralMeta"
}
]
}, 
{
"@about": "#otu412475", 
"@id": "otu412475", 
"@label": "Skeletonema costatum", 
"meta": [
{
"$": 569306, 
"@property": "ot:ottId", 
"@xsi:type": "nex:LiteralMeta"
}, 
{
"$": "Tl69709", 
"@property": "ot:treebaseOTUId", 
"@xsi:type": "nex:LiteralMeta"
}, 
{
"$": "Skeletonema costatum B212", 
"@property": "ot:originalLabel", 
"@xsi:type": "nex:LiteralMeta"
}
]
}, 
{
"@about": "#otu412476", 
"@id": "otu412476", 
"@label": "Skeletonema marinoi", 
"meta": [
{
"$": 810369, 
"@property": "ot:ottId", 
"@xsi:type": "nex:LiteralMeta"
}, 
{
"$": "Tl69710", 
"@property": "ot:treebaseOTUId", 
"@xsi:type": "nex:LiteralMeta"
}, 
{
"$": "Skeletonema marinoi CAN A1", 
"@property": "ot:originalLabel", 
"@xsi:type": "nex:LiteralMeta"
}
]
}, 
{
"@about": "#otu412477", 
"@id": "otu412477", 
"@label": "Skeletonema tropicum", 
"meta": [
{
"$": 441574, 
"@property": "ot:ottId", 
"@xsi:type": "nex:LiteralMeta"
}, 
{
"$": "Tl69711", 
"@property": "ot:treebaseOTUId", 
"@xsi:type": "nex:LiteralMeta"
}, 
{
"$": "Skeletonema tropicum CS605", 
"@property": "ot:originalLabel", 
"@xsi:type": "nex:LiteralMeta"
}
]
}, 
{
"@about": "#otu412478", 
"@id": "otu412478", 
"@label": "Skeletonema costatum", 
"meta": [
{
"$": 569306, 
"@property": "ot:ottId", 
"@xsi:type": "nex:LiteralMeta"
}, 
{
"$": "Tl69712", 
"@property": "ot:treebaseOTUId", 
"@xsi:type": "nex:LiteralMeta"
}, 
{
"$": "Skeletonema costatum B203", 
"@property": "ot:originalLabel", 
"@xsi:type": "nex:LiteralMeta"
}
]
}, 
{
"@about": "#otu412479", 
"@id": "otu412479", 
"@label": "Skeletonema menzellii", 
"meta": [
{
"$": 322452, 
"@property": "ot:ottId", 
"@xsi:type": "nex:LiteralMeta"
}, 
{
"$": "Tl69713", 
"@property": "ot:treebaseOTUId", 
"@xsi:type": "nex:LiteralMeta"
}, 
{
"$": "Skeletonema menzelii CCMP786", 
"@property": "ot:originalLabel", 
"@xsi:type": "nex:LiteralMeta"
}
]
}, 
{
"@about": "#otu412480", 
"@id": "otu412480", 
"@label": "Skeletonema marinoi", 
"meta": [
{
"$": 810369, 
"@property": "ot:ottId", 
"@xsi:type": "nex:LiteralMeta"
}, 
{
"$": "Tl69714", 
"@property": "ot:treebaseOTUId", 
"@xsi:type": "nex:LiteralMeta"
}, 
{
"$": "Skeletonema marinoi 7A3", 
"@property": "ot:originalLabel", 
"@xsi:type": "nex:LiteralMeta"
}
]
}, 
{
"@about": "#otu412481", 
"@id": "otu412481", 
"@label": "Skeletonema marinoi", 
"meta": [
{
"$": 810369, 
"@property": "ot:ottId", 
"@xsi:type": "nex:LiteralMeta"
}, 
{
"$": "Tl69715", 
"@property": "ot:treebaseOTUId", 
"@xsi:type": "nex:LiteralMeta"
}, 
{
"$": "Skeletonema marinoi AdrN5str2", 
"@property": "ot:originalLabel", 
"@xsi:type": "nex:LiteralMeta"
}
]
}, 
{
"@about": "#otu412482", 
"@id": "otu412482", 
"@label": "Thalassiosira rotula", 
"meta": [
{
"$": 601256, 
"@property": "ot:ottId", 
"@xsi:type": "nex:LiteralMeta"
}, 
{
"$": "Tl69716", 
"@property": "ot:treebaseOTUId", 
"@xsi:type": "nex:LiteralMeta"
}, 
{
"$": "Thalassiosira rotula CCAP1806", 
"@property": "ot:originalLabel", 
"@xsi:type": "nex:LiteralMeta"
}
]
}, 
{
"@about": "#otu412483", 
"@id": "otu412483", 
"@label": "Skeletonema grevillei", 
"meta": [
{
"$": 777861, 
"@property": "ot:ottId", 
"@xsi:type": "nex:LiteralMeta"
}, 
{
"$": "Tl69717", 
"@property": "ot:treebaseOTUId", 
"@xsi:type": "nex:LiteralMeta"
}, 
{
"$": "Skeletonema grevillei CCMP1685", 
"@property": "ot:originalLabel", 
"@xsi:type": "nex:LiteralMeta"
}
]
}, 
{
"@about": "#otu412484", 
"@id": "otu412484", 
"@label": "Skeletonema dohrnii", 
"meta": [
{
"$": 810367, 
"@property": "ot:ottId", 
"@xsi:type": "nex:LiteralMeta"
}, 
{
"$": "Tl69718", 
"@property": "ot:treebaseOTUId", 
"@xsi:type": "nex:LiteralMeta"
}, 
{
"$": "Skeletonema dohrnii CCMP1715", 
"@property": "ot:originalLabel", 
"@xsi:type": "nex:LiteralMeta"
}
]
}, 
{
"@about": "#otu412485", 
"@id": "otu412485", 
"@label": "Skeletonema marinoi", 
"meta": [
{
"$": 810369, 
"@property": "ot:ottId", 
"@xsi:type": "nex:LiteralMeta"
}, 
{
"$": "Tl69719", 
"@property": "ot:treebaseOTUId", 
"@xsi:type": "nex:LiteralMeta"
}, 
{
"$": "Skeletonema marinoi AdrN5str11", 
"@property": "ot:originalLabel", 
"@xsi:type": "nex:LiteralMeta"
}
]
}, 
{
"@about": "#otu412486", 
"@id": "otu412486", 
"@label": "Skeletonema marinoi", 
"meta": [
{
"$": 810369, 
"@property": "ot:ottId", 
"@xsi:type": "nex:LiteralMeta"
}, 
{
"$": "Tl69720", 
"@property": "ot:treebaseOTUId", 
"@xsi:type": "nex:LiteralMeta"
}, 
{
"$": "Skeletonema marinoi CCMP1009", 
"@property": "ot:originalLabel", 
"@xsi:type": "nex:LiteralMeta"
}
]
}, 
{
"@about": "#otu412487", 
"@id": "otu412487", 
"@label": "Skeletonema japonicum", 
"meta": [
{
"$": 441575, 
"@property": "ot:ottId", 
"@xsi:type": "nex:LiteralMeta"
}, 
{
"$": "Tl69721", 
"@property": "ot:treebaseOTUId", 
"@xsi:type": "nex:LiteralMeta"
}, 
{
"$": "Skeletonema japonicum Nar4W", 
"@property": "ot:originalLabel", 
"@xsi:type": "nex:LiteralMeta"
}
]
}, 
{
"@about": "#otu412488", 
"@id": "otu412488", 
"@label": "Thalassiosira rotula", 
"meta": [
{
"$": 601256, 
"@property": "ot:ottId", 
"@xsi:type": "nex:LiteralMeta"
}, 
{
"$": "Tl69722", 
"@property": "ot:treebaseOTUId", 
"@xsi:type": "nex:LiteralMeta"
}, 
{
"$": "Thalassiosira rotula CCMP1018", 
"@property": "ot:originalLabel", 
"@xsi:type": "nex:LiteralMeta"
}
]
}, 
{
"@about": "#otu412489", 
"@id": "otu412489", 
"@label": "Skeletonema japonicum", 
"meta": [
{
"$": 441575, 
"@property": "ot:ottId", 
"@xsi:type": "nex:LiteralMeta"
}, 
{
"$": "Tl69723", 
"@property": "ot:treebaseOTUId", 
"@xsi:type": "nex:LiteralMeta"
}, 
{
"$": "Skeletonema japonicum CCMP1283", 
"@property": "ot:originalLabel", 
"@xsi:type": "nex:LiteralMeta"
}
]
}, 
{
"@about": "#otu412490", 
"@id": "otu412490", 
"@label": "Skeletonema marinoi", 
"meta": [
{
"$": 810369, 
"@property": "ot:ottId", 
"@xsi:type": "nex:LiteralMeta"
}, 
{
"$": "Tl69724", 
"@property": "ot:treebaseOTUId", 
"@xsi:type": "nex:LiteralMeta"
}, 
{
"$": "Skeletonema marinoi B205", 
"@property": "ot:originalLabel", 
"@xsi:type": "nex:LiteralMeta"
}
]
}, 
{
"@about": "#otu412491", 
"@id": "otu412491", 
"@label": "Skeletonema menzellii", 
"meta": [
{
"$": 322452, 
"@property": "ot:ottId", 
"@xsi:type": "nex:LiteralMeta"
}, 
{
"$": "Tl69725", 
"@property": "ot:treebaseOTUId", 
"@xsi:type": "nex:LiteralMeta"
}, 
{
"$": "Skeletonema menzelii B83", 
"@property": "ot:originalLabel", 
"@xsi:type": "nex:LiteralMeta"
}
]
}, 
{
"@about": "#otu412492", 
"@id": "otu412492", 
"@label": "Skeletonema tropicum", 
"meta": [
{
"$": 441574, 
"@property": "ot:ottId", 
"@xsi:type": "nex:LiteralMeta"
}, 
{
"$": "Tl69726", 
"@property": "ot:treebaseOTUId", 
"@xsi:type": "nex:LiteralMeta"
}, 
{
"$": "Skeletonema tropicum CCMP778", 
"@property": "ot:originalLabel", 
"@xsi:type": "nex:LiteralMeta"
}
]
}, 
{
"@about": "#otu412493", 
"@id": "otu412493", 
"@label": "taxon 213", 
"meta": [
{
"$": "Tl69727", 
"@property": "ot:treebaseOTUId", 
"@xsi:type": "nex:LiteralMeta"
}, 
{
"$": "taxon 213", 
"@property": "ot:originalLabel", 
"@xsi:type": "nex:LiteralMeta"
}
]
}, 
{
"@about": "#otu412494", 
"@id": "otu412494", 
"@label": "Skeletonema marinoi", 
"meta": [
{
"$": 810369, 
"@property": "ot:ottId", 
"@xsi:type": "nex:LiteralMeta"
}, 
{
"$": "Tl69728", 
"@property": "ot:treebaseOTUId", 
"@xsi:type": "nex:LiteralMeta"
}, 
{
"$": "Skeletonema marinoi KF N2", 
"@property": "ot:originalLabel", 
"@xsi:type": "nex:LiteralMeta"
}
]
}, 
{
"@about": "#otu412495", 
"@id": "otu412495", 
"@label": "Skeletonema marinoi", 
"meta": [
{
"$": 810369, 
"@property": "ot:ottId", 
"@xsi:type": "nex:LiteralMeta"
}, 
{
"$": "Tl69729", 
"@property": "ot:treebaseOTUId", 
"@xsi:type": "nex:LiteralMeta"
}, 
{
"$": "Skeletonema marinoi B216", 
"@property": "ot:originalLabel", 
"@xsi:type": "nex:LiteralMeta"
}
]
}, 
{
"@about": "#otu412496", 
"@id": "otu412496", 
"@label": "Skeletonema ardens", 
"meta": [
{
"$": 777867, 
"@property": "ot:ottId", 
"@xsi:type": "nex:LiteralMeta"
}, 
{
"$": "Tl69730", 
"@property": "ot:treebaseOTUId", 
"@xsi:type": "nex:LiteralMeta"
}, 
{
"$": "Skeletonema ardens CCMP794", 
"@property": "ot:originalLabel", 
"@xsi:type": "nex:LiteralMeta"
}
]
}, 
{
"@about": "#otu412497", 
"@id": "otu412497", 
"@label": "Skeletonema marinoi", 
"meta": [
{
"$": 810369, 
"@property": "ot:ottId", 
"@xsi:type": "nex:LiteralMeta"
}, 
{
"$": "Tl69731", 
"@property": "ot:treebaseOTUId", 
"@xsi:type": "nex:LiteralMeta"
}, 
{
"$": "Skeletonema marinoi CAN E2", 
"@property": "ot:originalLabel", 
"@xsi:type": "nex:LiteralMeta"
}
]
}, 
{
"@about": "#otu412498", 
"@id": "otu412498", 
"@label": "Skeletonema japonicum", 
"meta": [
{
"$": 441575, 
"@property": "ot:ottId", 
"@xsi:type": "nex:LiteralMeta"
}, 
{
"$": "Tl69732", 
"@property": "ot:treebaseOTUId", 
"@xsi:type": "nex:LiteralMeta"
}, 
{
"$": "Skeletonema japonicum KoreaCS24", 
"@property": "ot:originalLabel", 
"@xsi:type": "nex:LiteralMeta"
}
]
}, 
{
"@about": "#otu412499", 
"@id": "otu412499", 
"@label": "Skeletonema pseudocostatum", 
"meta": [
{
"$": 459898, 
"@property": "ot:ottId", 
"@xsi:type": "nex:LiteralMeta"
}, 
{
"$": "Tl69733", 
"@property": "ot:treebaseOTUId", 
"@xsi:type": "nex:LiteralMeta"
}, 
{
"$": "Skeletonema pseudocostatum B139", 
"@property": "ot:originalLabel", 
"@xsi:type": "nex:LiteralMeta"
}
]
}, 
{
"@about": "#otu412500", 
"@id": "otu412500", 
"@label": "Skeletonema costatum", 
"meta": [
{
"$": 569306, 
"@property": "ot:ottId", 
"@xsi:type": "nex:LiteralMeta"
}, 
{
"$": "Tl69734", 
"@property": "ot:treebaseOTUId", 
"@xsi:type": "nex:LiteralMeta"
}, 
{
"$": "Skeletonema costatum B207", 
"@property": "ot:originalLabel", 
"@xsi:type": "nex:LiteralMeta"
}
]
}, 
{
"@about": "#otu412501", 
"@id": "otu412501", 
"@label": "Skeletonema dohrnii", 
"meta": [
{
"$": 810367, 
"@property": "ot:ottId", 
"@xsi:type": "nex:LiteralMeta"
}, 
{
"$": "Tl69735", 
"@property": "ot:treebaseOTUId", 
"@xsi:type": "nex:LiteralMeta"
}, 
{
"$": "Skeletonema dohrnii CCMP785", 
"@property": "ot:originalLabel", 
"@xsi:type": "nex:LiteralMeta"
}
]
}, 
{
"@about": "#otu412502", 
"@id": "otu412502", 
"@label": "Skeletonema dohrnii", 
"meta": [
{
"$": 810367, 
"@property": "ot:ottId", 
"@xsi:type": "nex:LiteralMeta"
}, 
{
"$": "Tl69736", 
"@property": "ot:treebaseOTUId", 
"@xsi:type": "nex:LiteralMeta"
}, 
{
"$": "Skeletonema dohrnii SFBst21", 
"@property": "ot:originalLabel", 
"@xsi:type": "nex:LiteralMeta"
}
]
}, 
{
"@about": "#otu412503", 
"@id": "otu412503", 
"@label": "Skeletonema tropicum", 
"meta": [
{
"$": 441574, 
"@property": "ot:ottId", 
"@xsi:type": "nex:LiteralMeta"
}, 
{
"$": "Tl69737", 
"@property": "ot:treebaseOTUId", 
"@xsi:type": "nex:LiteralMeta"
}, 
{
"$": "Skeletonema tropicum B141", 
"@property": "ot:originalLabel", 
"@xsi:type": "nex:LiteralMeta"
}
]
}, 
{
"@about": "#otu412504", 
"@id": "otu412504", 
"@label": "Skeletonema marinoi", 
"meta": [
{
"$": 810369, 
"@property": "ot:ottId", 
"@xsi:type": "nex:LiteralMeta"
}, 
{
"$": "Tl69738", 
"@property": "ot:treebaseOTUId", 
"@xsi:type": "nex:LiteralMeta"
}, 
{
"$": "Skeletonema marinoi FE48", 
"@property": "ot:originalLabel", 
"@xsi:type": "nex:LiteralMeta"
}
]
}, 
{
"@about": "#otu412505", 
"@id": "otu412505", 
"@label": "Skeletonema pseudocostatum", 
"meta": [
{
"$": 459898, 
"@property": "ot:ottId", 
"@xsi:type": "nex:LiteralMeta"
}, 
{
"$": "Tl69739", 
"@property": "ot:treebaseOTUId", 
"@xsi:type": "nex:LiteralMeta"
}, 
{
"$": "Skeletonema pseudocostatum CS36", 
"@property": "ot:originalLabel", 
"@xsi:type": "nex:LiteralMeta"
}
]
}, 
{
"@about": "#otu412506", 
"@id": "otu412506", 
"@label": "Skeletonema dohrnii", 
"meta": [
{
"$": 810367, 
"@property": "ot:ottId", 
"@xsi:type": "nex:LiteralMeta"
}, 
{
"$": "Tl69740", 
"@property": "ot:treebaseOTUId", 
"@xsi:type": "nex:LiteralMeta"
}, 
{
"$": "Skeletonema dohrnii SK FQ", 
"@property": "ot:originalLabel", 
"@xsi:type": "nex:LiteralMeta"
}
]
}, 
{
"@about": "#otu412507", 
"@id": "otu412507", 
"@label": "Skeletonema pseudocostatum", 
"meta": [
{
"$": 459898, 
"@property": "ot:ottId", 
"@xsi:type": "nex:LiteralMeta"
}, 
{
"$": "Tl69741", 
"@property": "ot:treebaseOTUId", 
"@xsi:type": "nex:LiteralMeta"
}, 
{
"$": "Skeletonema pseudocostatum B81", 
"@property": "ot:originalLabel", 
"@xsi:type": "nex:LiteralMeta"
}
]
}, 
{
"@about": "#otu412508", 
"@id": "otu412508", 
"@label": "Thalassiosira rotula", 
"meta": [
{
"$": 601256, 
"@property": "ot:ottId", 
"@xsi:type": "nex:LiteralMeta"
}, 
{
"$": "Tl69742", 
"@property": "ot:treebaseOTUId", 
"@xsi:type": "nex:LiteralMeta"
}, 
{
"$": "Thalassiosira rotula CCMP1647", 
"@property": "ot:originalLabel", 
"@xsi:type": "nex:LiteralMeta"
}
]
}, 
{
"@about": "#otu412509", 
"@id": "otu412509", 
"@label": "Skeletonema tropicum", 
"meta": [
{
"$": 441574, 
"@property": "ot:ottId", 
"@xsi:type": "nex:LiteralMeta"
}, 
{
"$": "Tl69743", 
"@property": "ot:treebaseOTUId", 
"@xsi:type": "nex:LiteralMeta"
}, 
{
"$": "Skeletonema tropicum B205", 
"@property": "ot:originalLabel", 
"@xsi:type": "nex:LiteralMeta"
}
]
}, 
{
"@about": "#otu412510", 
"@id": "otu412510", 
"@label": "Skeletonema marinoi", 
"meta": [
{
"$": 810369, 
"@property": "ot:ottId", 
"@xsi:type": "nex:LiteralMeta"
}, 
{
"$": "Tl69744", 
"@property": "ot:treebaseOTUId", 
"@xsi:type": "nex:LiteralMeta"
}, 
{
"$": "Skeletonema marinoi FE45", 
"@property": "ot:originalLabel", 
"@xsi:type": "nex:LiteralMeta"
}
]
}, 
{
"@about": "#otu412511", 
"@id": "otu412511", 
"@label": "Skeletonema menzellii", 
"meta": [
{
"$": 322452, 
"@property": "ot:ottId", 
"@xsi:type": "nex:LiteralMeta"
}, 
{
"$": "Tl69745", 
"@property": "ot:treebaseOTUId", 
"@xsi:type": "nex:LiteralMeta"
}, 
{
"$": "Skeletonema menzelii CCMP787", 
"@property": "ot:originalLabel", 
"@xsi:type": "nex:LiteralMeta"
}
]
}, 
{
"@about": "#otu412512", 
"@id": "otu412512", 
"@label": "Skeletonema dohrnii", 
"meta": [
{
"$": 810367, 
"@property": "ot:ottId", 
"@xsi:type": "nex:LiteralMeta"
}, 
{
"$": "Tl69746", 
"@property": "ot:treebaseOTUId", 
"@xsi:type": "nex:LiteralMeta"
}, 
{
"$": "Skeletonema dohrnii SFB32 2", 
"@property": "ot:originalLabel", 
"@xsi:type": "nex:LiteralMeta"
}
]
}, 
{
"@about": "#otu412513", 
"@id": "otu412513", 
"@label": "Skeletonema grethae", 
"meta": [
{
"$": 810365, 
"@property": "ot:ottId", 
"@xsi:type": "nex:LiteralMeta"
}, 
{
"$": "Tl69747", 
"@property": "ot:treebaseOTUId", 
"@xsi:type": "nex:LiteralMeta"
}, 
{
"$": "Skeletonema grethae NOAA D3", 
"@property": "ot:originalLabel", 
"@xsi:type": "nex:LiteralMeta"
}
]
}, 
{
"@about": "#otu412514", 
"@id": "otu412514", 
"@label": "Skeletonema costatum", 
"meta": [
{
"$": 569306, 
"@property": "ot:ottId", 
"@xsi:type": "nex:LiteralMeta"
}, 
{
"$": "Tl69748", 
"@property": "ot:treebaseOTUId", 
"@xsi:type": "nex:LiteralMeta"
}, 
{
"$": "Skeletonema costatum B211", 
"@property": "ot:originalLabel", 
"@xsi:type": "nex:LiteralMeta"
}
]
}, 
{
"@about": "#otu412515", 
"@id": "otu412515", 
"@label": "Skeletonema japonicum", 
"meta": [
{
"$": 441575, 
"@property": "ot:ottId", 
"@xsi:type": "nex:LiteralMeta"
}, 
{
"$": "Tl69749", 
"@property": "ot:treebaseOTUId", 
"@xsi:type": "nex:LiteralMeta"
}, 
{
"$": "Skeletonema japonicum Nar2W", 
"@property": "ot:originalLabel", 
"@xsi:type": "nex:LiteralMeta"
}
]
}, 
{
"@about": "#otu412516", 
"@id": "otu412516", 
"@label": "Skeletonema costatum", 
"meta": [
{
"$": 569306, 
"@property": "ot:ottId", 
"@xsi:type": "nex:LiteralMeta"
}, 
{
"$": "Tl69750", 
"@property": "ot:treebaseOTUId", 
"@xsi:type": "nex:LiteralMeta"
}, 
{
"$": "Skeletonema costatum SK DH", 
"@property": "ot:originalLabel", 
"@xsi:type": "nex:LiteralMeta"
}
]
}, 
{
"@about": "#otu412517", 
"@id": "otu412517", 
"@label": "Skeletonema dohrnii", 
"meta": [
{
"$": 810367, 
"@property": "ot:ottId", 
"@xsi:type": "nex:LiteralMeta"
}, 
{
"$": "Tl69751", 
"@property": "ot:treebaseOTUId", 
"@xsi:type": "nex:LiteralMeta"
}, 
{
"$": "Skeletonema dohrnii CCMP789", 
"@property": "ot:originalLabel", 
"@xsi:type": "nex:LiteralMeta"
}
]
}, 
{
"@about": "#otu412518", 
"@id": "otu412518", 
"@label": "Skeletonema marinoi", 
"meta": [
{
"$": 810369, 
"@property": "ot:ottId", 
"@xsi:type": "nex:LiteralMeta"
}, 
{
"$": "Tl69752", 
"@property": "ot:treebaseOTUId", 
"@xsi:type": "nex:LiteralMeta"
}, 
{
"$": "Skeletonema marinoi KAL C3", 
"@property": "ot:originalLabel", 
"@xsi:type": "nex:LiteralMeta"
}
]
}, 
{
"@about": "#otu412519", 
"@id": "otu412519", 
"@label": "Skeletonema pseudocostatum", 
"meta": [
{
"$": 459898, 
"@property": "ot:ottId", 
"@xsi:type": "nex:LiteralMeta"
}, 
{
"$": "Tl69753", 
"@property": "ot:treebaseOTUId", 
"@xsi:type": "nex:LiteralMeta"
}, 
{
"$": "Skeletonema pseudocostatum D1", 
"@property": "ot:originalLabel", 
"@xsi:type": "nex:LiteralMeta"
}
]
}, 
{
"@about": "#otu412520", 
"@id": "otu412520", 
"@label": "Skeletonema dohrnii", 
"meta": [
{
"$": 810367, 
"@property": "ot:ottId", 
"@xsi:type": "nex:LiteralMeta"
}, 
{
"$": "Tl69754", 
"@property": "ot:treebaseOTUId", 
"@xsi:type": "nex:LiteralMeta"
}, 
{
"$": "Skeletonema dohrnii B191", 
"@property": "ot:originalLabel", 
"@xsi:type": "nex:LiteralMeta"
}
]
}, 
{
"@about": "#otu412521", 
"@id": "otu412521", 
"@label": "Skeletonema marinoi", 
"meta": [
{
"$": 810369, 
"@property": "ot:ottId", 
"@xsi:type": "nex:LiteralMeta"
}, 
{
"$": "Tl69755", 
"@property": "ot:treebaseOTUId", 
"@xsi:type": "nex:LiteralMeta"
}, 
{
"$": "Skeletonema marinoi FE43R", 
"@property": "ot:originalLabel", 
"@xsi:type": "nex:LiteralMeta"
}
]
}, 
{
"@about": "#otu412522", 
"@id": "otu412522", 
"@label": "Skeletonema marinoi", 
"meta": [
{
"$": 810369, 
"@property": "ot:ottId", 
"@xsi:type": "nex:LiteralMeta"
}, 
{
"$": "Tl69756", 
"@property": "ot:treebaseOTUId", 
"@xsi:type": "nex:LiteralMeta"
}, 
{
"$": "Skeletonema marinoi B146", 
"@property": "ot:originalLabel", 
"@xsi:type": "nex:LiteralMeta"
}
]
}, 
{
"@about": "#otu412523", 
"@id": "otu412523", 
"@label": "Skeletonema japonicum", 
"meta": [
{
"$": 441575, 
"@property": "ot:ottId", 
"@xsi:type": "nex:LiteralMeta"
}, 
{
"$": "Tl69757", 
"@property": "ot:treebaseOTUId", 
"@xsi:type": "nex:LiteralMeta"
}, 
{
"$": "Skeletonema japonicum CCMP784", 
"@property": "ot:originalLabel", 
"@xsi:type": "nex:LiteralMeta"
}
]
}, 
{
"@about": "#otu412524", 
"@id": "otu412524", 
"@label": "Skeletonema marinoi", 
"meta": [
{
"$": 810369, 
"@property": "ot:ottId", 
"@xsi:type": "nex:LiteralMeta"
}, 
{
"$": "Tl69758", 
"@property": "ot:treebaseOTUId", 
"@xsi:type": "nex:LiteralMeta"
}, 
{
"$": "Skeletonema marinoi AdrN5str3", 
"@property": "ot:originalLabel", 
"@xsi:type": "nex:LiteralMeta"
}
]
}, 
{
"@about": "#otu412525", 
"@id": "otu412525", 
"@label": "Skeletonema dohrnii", 
"meta": [
{
"$": 810367, 
"@property": "ot:ottId", 
"@xsi:type": "nex:LiteralMeta"
}, 
{
"$": "Tl69759", 
"@property": "ot:treebaseOTUId", 
"@xsi:type": "nex:LiteralMeta"
}, 
{
"$": "Skeletonema dohrnii CCMP779", 
"@property": "ot:originalLabel", 
"@xsi:type": "nex:LiteralMeta"
}
]
}, 
{
"@about": "#otu412526", 
"@id": "otu412526", 
"@label": "Skeletonema tropicum", 
"meta": [
{
"$": 441574, 
"@property": "ot:ottId", 
"@xsi:type": "nex:LiteralMeta"
}, 
{
"$": "Tl69760", 
"@property": "ot:treebaseOTUId", 
"@xsi:type": "nex:LiteralMeta"
}, 
{
"$": "Skeletonema tropicum SCXM03", 
"@property": "ot:originalLabel", 
"@xsi:type": "nex:LiteralMeta"
}
]
}, 
{
"@about": "#otu412527", 
"@id": "otu412527", 
"@label": "Skeletonema pseudocostatum", 
"meta": [
{
"$": 459898, 
"@property": "ot:ottId", 
"@xsi:type": "nex:LiteralMeta"
}, 
{
"$": "Tl69761", 
"@property": "ot:treebaseOTUId", 
"@xsi:type": "nex:LiteralMeta"
}, 
{
"$": "Skeletonema pseudocostatum D2", 
"@property": "ot:originalLabel", 
"@xsi:type": "nex:LiteralMeta"
}
]
}, 
{
"@about": "#otu412528", 
"@id": "otu412528", 
"@label": "Skeletonema tropicum", 
"meta": [
{
"$": 441574, 
"@property": "ot:ottId", 
"@xsi:type": "nex:LiteralMeta"
}, 
{
"$": "Tl69762", 
"@property": "ot:treebaseOTUId", 
"@xsi:type": "nex:LiteralMeta"
}, 
{
"$": "Skeletonema tropicum CCMP788b", 
"@property": "ot:originalLabel", 
"@xsi:type": "nex:LiteralMeta"
}
]
}, 
{
"@about": "#otu412529", 
"@id": "otu412529", 
"@label": "Skeletonema pseudocostatum", 
"meta": [
{
"$": 459898, 
"@property": "ot:ottId", 
"@xsi:type": "nex:LiteralMeta"
}, 
{
"$": "Tl69763", 
"@property": "ot:treebaseOTUId", 
"@xsi:type": "nex:LiteralMeta"
}, 
{
"$": "Skeletonema pseudocostatum B80", 
"@property": "ot:originalLabel", 
"@xsi:type": "nex:LiteralMeta"
}
]
}, 
{
"@about": "#otu412530", 
"@id": "otu412530", 
"@label": "Skeletonema marinoi", 
"meta": [
{
"$": 810369, 
"@property": "ot:ottId", 
"@xsi:type": "nex:LiteralMeta"
}, 
{
"$": "Tl69764", 
"@property": "ot:treebaseOTUId", 
"@xsi:type": "nex:LiteralMeta"
}, 
{
"$": "Skeletonema marinoi FE42R", 
"@property": "ot:originalLabel", 
"@xsi:type": "nex:LiteralMeta"
}
]
}, 
{
"@about": "#otu412531", 
"@id": "otu412531", 
"@label": "Skeletonema costatum", 
"meta": [
{
"$": 569306, 
"@property": "ot:ottId", 
"@xsi:type": "nex:LiteralMeta"
}, 
{
"$": "Tl69765", 
"@property": "ot:treebaseOTUId", 
"@xsi:type": "nex:LiteralMeta"
}, 
{
"$": "Skeletonema costatum B202", 
"@property": "ot:originalLabel", 
"@xsi:type": "nex:LiteralMeta"
}
]
}, 
{
"@about": "#otu412532", 
"@id": "otu412532", 
"@label": "Skeletonema tropicum", 
"meta": [
{
"$": 441574, 
"@property": "ot:ottId", 
"@xsi:type": "nex:LiteralMeta"
}, 
{
"$": "Tl69766", 
"@property": "ot:treebaseOTUId", 
"@xsi:type": "nex:LiteralMeta"
}, 
{
"$": "Skeletonema tropicum B209", 
"@property": "ot:originalLabel", 
"@xsi:type": "nex:LiteralMeta"
}
]
}, 
{
"@about": "#otu412533", 
"@id": "otu412533", 
"@label": "Skeletonema marinoi", 
"meta": [
{
"$": 810369, 
"@property": "ot:ottId", 
"@xsi:type": "nex:LiteralMeta"
}, 
{
"$": "Tl69767", 
"@property": "ot:treebaseOTUId", 
"@xsi:type": "nex:LiteralMeta"
}, 
{
"$": "Skeletonema marinoi CAN B2", 
"@property": "ot:originalLabel", 
"@xsi:type": "nex:LiteralMeta"
}
]
}, 
{
"@about": "#otu412534", 
"@id": "otu412534", 
"@label": "Skeletonema costatum", 
"meta": [
{
"$": 569306, 
"@property": "ot:ottId", 
"@xsi:type": "nex:LiteralMeta"
}, 
{
"$": "Tl69768", 
"@property": "ot:treebaseOTUId", 
"@xsi:type": "nex:LiteralMeta"
}, 
{
"$": "Skeletonema costatum SK XM", 
"@property": "ot:originalLabel", 
"@xsi:type": "nex:LiteralMeta"
}
]
}, 
{
"@about": "#otu412535", 
"@id": "otu412535", 
"@label": "Thalassiosira", 
"meta": [
{
"$": 753591, 
"@property": "ot:ottId", 
"@xsi:type": "nex:LiteralMeta"
}, 
{
"$": "Tl69769", 
"@property": "ot:treebaseOTUId", 
"@xsi:type": "nex:LiteralMeta"
}, 
{
"$": "Thalassiosira sp. SZNB101", 
"@property": "ot:originalLabel", 
"@xsi:type": "nex:LiteralMeta"
}
]
}, 
{
"@about": "#otu412536", 
"@id": "otu412536", 
"@label": "Skeletonema tropicum", 
"meta": [
{
"$": 441574, 
"@property": "ot:ottId", 
"@xsi:type": "nex:LiteralMeta"
}, 
{
"$": "Tl69770", 
"@property": "ot:treebaseOTUId", 
"@xsi:type": "nex:LiteralMeta"
}, 
{
"$": "Skeletonema tropicum D", 
"@property": "ot:originalLabel", 
"@xsi:type": "nex:LiteralMeta"
}
]
}, 
{
"@about": "#otu412537", 
"@id": "otu412537", 
"@label": "Skeletonema dohrnii", 
"meta": [
{
"$": 810367, 
"@property": "ot:ottId", 
"@xsi:type": "nex:LiteralMeta"
}, 
{
"$": "Tl69771", 
"@property": "ot:treebaseOTUId", 
"@xsi:type": "nex:LiteralMeta"
}, 
{
"$": "Skeletonema dohrnii SCTD01", 
"@property": "ot:originalLabel", 
"@xsi:type": "nex:LiteralMeta"
}
]
}, 
{
"@about": "#otu412538", 
"@id": "otu412538", 
"@label": "Skeletonema pseudocostatum", 
"meta": [
{
"$": 459898, 
"@property": "ot:ottId", 
"@xsi:type": "nex:LiteralMeta"
}, 
{
"$": "Tl69772", 
"@property": "ot:treebaseOTUId", 
"@xsi:type": "nex:LiteralMeta"
}, 
{
"$": "Skeletonema pseudocostatum B79", 
"@property": "ot:originalLabel", 
"@xsi:type": "nex:LiteralMeta"
}
]
}, 
{
"@about": "#otu412539", 
"@id": "otu412539", 
"@label": "Skeletonema marinoi", 
"meta": [
{
"$": 810369, 
"@property": "ot:ottId", 
"@xsi:type": "nex:LiteralMeta"
}, 
{
"$": "Tl69773", 
"@property": "ot:treebaseOTUId", 
"@xsi:type": "nex:LiteralMeta"
}, 
{
"$": "Skeletonema marinoi KF S2", 
"@property": "ot:originalLabel", 
"@xsi:type": "nex:LiteralMeta"
}
]
}, 
{
"@about": "#otu412540", 
"@id": "otu412540", 
"@label": "Skeletonema dohrnii", 
"meta": [
{
"$": 810367, 
"@property": "ot:ottId", 
"@xsi:type": "nex:LiteralMeta"
}, 
{
"$": "Tl69774", 
"@property": "ot:treebaseOTUId", 
"@xsi:type": "nex:LiteralMeta"
}, 
{
"$": "Skeletonema dohrnii NIES17", 
"@property": "ot:originalLabel", 
"@xsi:type": "nex:LiteralMeta"
}
]
}, 
{
"@about": "#otu412541", 
"@id": "otu412541", 
"@label": "Skeletonema subsalsum", 
"meta": [
{
"$": 1024259, 
"@property": "ot:ottId", 
"@xsi:type": "nex:LiteralMeta"
}, 
{
"$": "Tl69775", 
"@property": "ot:treebaseOTUId", 
"@xsi:type": "nex:LiteralMeta"
}, 
{
"$": "Skeletonema subsalsum CCAP1077", 
"@property": "ot:originalLabel", 
"@xsi:type": "nex:LiteralMeta"
}
]
}, 
{
"@about": "#otu412542", 
"@id": "otu412542", 
"@label": "Skeletonema grethae", 
"meta": [
{
"$": 810365, 
"@property": "ot:ottId", 
"@xsi:type": "nex:LiteralMeta"
}, 
{
"$": "Tl69776", 
"@property": "ot:treebaseOTUId", 
"@xsi:type": "nex:LiteralMeta"
}, 
{
"$": "Skeletonema grethae CCMP776", 
"@property": "ot:originalLabel", 
"@xsi:type": "nex:LiteralMeta"
}
]
}, 
{
"@about": "#otu412543", 
"@id": "otu412543", 
"@label": "Skeletonema japonicum", 
"meta": [
{
"$": 441575, 
"@property": "ot:ottId", 
"@xsi:type": "nex:LiteralMeta"
}, 
{
"$": "Tl69777", 
"@property": "ot:treebaseOTUId", 
"@xsi:type": "nex:LiteralMeta"
}, 
{
"$": "Skeletonema japonicum CCMP1281", 
"@property": "ot:originalLabel", 
"@xsi:type": "nex:LiteralMeta"
}
]
}, 
{
"@about": "#otu412544", 
"@id": "otu412544", 
"@label": "Skeletonema marinoi", 
"meta": [
{
"$": 810369, 
"@property": "ot:ottId", 
"@xsi:type": "nex:LiteralMeta"
}, 
{
"$": "Tl69778", 
"@property": "ot:treebaseOTUId", 
"@xsi:type": "nex:LiteralMeta"
}, 
{
"$": "Skeletonema marinoi KAL H1", 
"@property": "ot:originalLabel", 
"@xsi:type": "nex:LiteralMeta"
}
]
}, 
{
"@about": "#otu412545", 
"@id": "otu412545", 
"@label": "Skeletonema pseudocostatum", 
"meta": [
{
"$": 459898, 
"@property": "ot:ottId", 
"@xsi:type": "nex:LiteralMeta"
}, 
{
"$": "Tl69779", 
"@property": "ot:treebaseOTUId", 
"@xsi:type": "nex:LiteralMeta"
}, 
{
"$": "Skeletonema pseudocostatum B77", 
"@property": "ot:originalLabel", 
"@xsi:type": "nex:LiteralMeta"
}
]
}, 
{
"@about": "#otu412546", 
"@id": "otu412546", 
"@label": "Skeletonema marinoi", 
"meta": [
{
"$": 810369, 
"@property": "ot:ottId", 
"@xsi:type": "nex:LiteralMeta"
}, 
{
"$": "Tl69780", 
"@property": "ot:treebaseOTUId", 
"@xsi:type": "nex:LiteralMeta"
}, 
{
"$": "Skeletonema marinoi PORT A3", 
"@property": "ot:originalLabel", 
"@xsi:type": "nex:LiteralMeta"
}
]
}, 
{
"@about": "#otu412547", 
"@id": "otu412547", 
"@label": "Skeletonema tropicum", 
"meta": [
{
"$": 441574, 
"@property": "ot:ottId", 
"@xsi:type": "nex:LiteralMeta"
}, 
{
"$": "Tl69781", 
"@property": "ot:treebaseOTUId", 
"@xsi:type": "nex:LiteralMeta"
}, 
{
"$": "Skeletonema tropicum B162", 
"@property": "ot:originalLabel", 
"@xsi:type": "nex:LiteralMeta"
}
]
}, 
{
"@about": "#otu412548", 
"@id": "otu412548", 
"@label": "Skeletonema pseudocostatum", 
"meta": [
{
"$": 459898, 
"@property": "ot:ottId", 
"@xsi:type": "nex:LiteralMeta"
}, 
{
"$": "Tl69782", 
"@property": "ot:treebaseOTUId", 
"@xsi:type": "nex:LiteralMeta"
}, 
{
"$": "Skeletonema pseudocostatum SCXM", 
"@property": "ot:originalLabel", 
"@xsi:type": "nex:LiteralMeta"
}
]
}, 
{
"@about": "#otu412549", 
"@id": "otu412549", 
"@label": "Skeletonema marinoi", 
"meta": [
{
"$": 810369, 
"@property": "ot:ottId", 
"@xsi:type": "nex:LiteralMeta"
}, 
{
"$": "Tl69783", 
"@property": "ot:treebaseOTUId", 
"@xsi:type": "nex:LiteralMeta"
}, 
{
"$": "Skeletonema marinoi CCMP781", 
"@property": "ot:originalLabel", 
"@xsi:type": "nex:LiteralMeta"
}
]
}, 
{
"@about": "#otu412550", 
"@id": "otu412550", 
"@label": "Skeletonema menzellii", 
"meta": [
{
"$": 322452, 
"@property": "ot:ottId", 
"@xsi:type": "nex:LiteralMeta"
}, 
{
"$": "Tl69784", 
"@property": "ot:treebaseOTUId", 
"@xsi:type": "nex:LiteralMeta"
}, 
{
"$": "Skeletonema menzelii B219", 
"@property": "ot:originalLabel", 
"@xsi:type": "nex:LiteralMeta"
}
]
}, 
{
"@about": "#otu412551", 
"@id": "otu412551", 
"@label": "Skeletonema japonicum", 
"meta": [
{
"$": 441575, 
"@property": "ot:ottId", 
"@xsi:type": "nex:LiteralMeta"
}, 
{
"$": "Tl69785", 
"@property": "ot:treebaseOTUId", 
"@xsi:type": "nex:LiteralMeta"
}, 
{
"$": "Skeletonema japonicum CS76", 
"@property": "ot:originalLabel", 
"@xsi:type": "nex:LiteralMeta"
}
]
}, 
{
"@about": "#otu412552", 
"@id": "otu412552", 
"@label": "Skeletonema grethae", 
"meta": [
{
"$": 810365, 
"@property": "ot:ottId", 
"@xsi:type": "nex:LiteralMeta"
}, 
{
"$": "Tl69786", 
"@property": "ot:treebaseOTUId", 
"@xsi:type": "nex:LiteralMeta"
}, 
{
"$": "Skeletonema grethae NOAA A1", 
"@property": "ot:originalLabel", 
"@xsi:type": "nex:LiteralMeta"
}
]
}, 
{
"@about": "#otu412553", 
"@id": "otu412553", 
"@label": "Skeletonema grethae", 
"meta": [
{
"$": 810365, 
"@property": "ot:ottId", 
"@xsi:type": "nex:LiteralMeta"
}, 
{
"$": "Tl69787", 
"@property": "ot:treebaseOTUId", 
"@xsi:type": "nex:LiteralMeta"
}, 
{
"$": "Skeletonema grethae B197", 
"@property": "ot:originalLabel", 
"@xsi:type": "nex:LiteralMeta"
}
]
}, 
{
"@about": "#otu412554", 
"@id": "otu412554", 
"@label": "Skeletonema grethae", 
"meta": [
{
"$": 810365, 
"@property": "ot:ottId", 
"@xsi:type": "nex:LiteralMeta"
}, 
{
"$": "Tl69788", 
"@property": "ot:treebaseOTUId", 
"@xsi:type": "nex:LiteralMeta"
}, 
{
"$": "Skeletonema grethae B190", 
"@property": "ot:originalLabel", 
"@xsi:type": "nex:LiteralMeta"
}
]
}, 
{
"@about": "#otu412555", 
"@id": "otu412555", 
"@label": "Skeletonema marinoi", 
"meta": [
{
"$": 810369, 
"@property": "ot:ottId", 
"@xsi:type": "nex:LiteralMeta"
}, 
{
"$": "Tl69789", 
"@property": "ot:treebaseOTUId", 
"@xsi:type": "nex:LiteralMeta"
}, 
{
"$": "Skeletonema marinoi B118", 
"@property": "ot:originalLabel", 
"@xsi:type": "nex:LiteralMeta"
}
]
}, 
{
"@about": "#otu412556", 
"@id": "otu412556", 
"@label": "Skeletonema tropicum", 
"meta": [
{
"$": 441574, 
"@property": "ot:ottId", 
"@xsi:type": "nex:LiteralMeta"
}, 
{
"$": "Tl69790", 
"@property": "ot:treebaseOTUId", 
"@xsi:type": "nex:LiteralMeta"
}, 
{
"$": "Skeletonema tropicum B210", 
"@property": "ot:originalLabel", 
"@xsi:type": "nex:LiteralMeta"
}
]
}, 
{
"@about": "#otu412557", 
"@id": "otu412557", 
"@label": "Skeletonema costatum", 
"meta": [
{
"$": 569306, 
"@property": "ot:ottId", 
"@xsi:type": "nex:LiteralMeta"
}, 
{
"$": "Tl69791", 
"@property": "ot:treebaseOTUId", 
"@xsi:type": "nex:LiteralMeta"
}, 
{
"$": "Skeletonema costatum B206", 
"@property": "ot:originalLabel", 
"@xsi:type": "nex:LiteralMeta"
}
]
}, 
{
"@about": "#otu412558", 
"@id": "otu412558", 
"@label": "Cyclotella", 
"meta": [
{
"$": 422797, 
"@property": "ot:ottId", 
"@xsi:type": "nex:LiteralMeta"
}, 
{
"$": "Tl69792", 
"@property": "ot:treebaseOTUId", 
"@xsi:type": "nex:LiteralMeta"
}, 
{
"$": "Cyclotella sp G18W42", 
"@property": "ot:originalLabel", 
"@xsi:type": "nex:LiteralMeta"
}
]
}, 
{
"@about": "#otu412559", 
"@id": "otu412559", 
"@label": "Skeletonema marinoi", 
"meta": [
{
"$": 810369, 
"@property": "ot:ottId", 
"@xsi:type": "nex:LiteralMeta"
}, 
{
"$": "Tl69793", 
"@property": "ot:treebaseOTUId", 
"@xsi:type": "nex:LiteralMeta"
}, 
{
"$": "Skeletonema marinoi FE40", 
"@property": "ot:originalLabel", 
"@xsi:type": "nex:LiteralMeta"
}
]
}, 
{
"@about": "#otu412560", 
"@id": "otu412560", 
"@label": "Skeletonema marinoi", 
"meta": [
{
"$": 810369, 
"@property": "ot:ottId", 
"@xsi:type": "nex:LiteralMeta"
}, 
{
"$": "Tl69794", 
"@property": "ot:treebaseOTUId", 
"@xsi:type": "nex:LiteralMeta"
}, 
{
"$": "Skeletonema marinoi FE44", 
"@property": "ot:originalLabel", 
"@xsi:type": "nex:LiteralMeta"
}
]
}, 
{
"@about": "#otu412561", 
"@id": "otu412561", 
"@label": "Skeletonema tropicum", 
"meta": [
{
"$": 441574, 
"@property": "ot:ottId", 
"@xsi:type": "nex:LiteralMeta"
}, 
{
"$": "Tl69795", 
"@property": "ot:treebaseOTUId", 
"@xsi:type": "nex:LiteralMeta"
}, 
{
"$": "Skeletonema tropicum M98", 
"@property": "ot:originalLabel", 
"@xsi:type": "nex:LiteralMeta"
}
]
}, 
{
"@about": "#otu412562", 
"@id": "otu412562", 
"@label": "Skeletonema costatum", 
"meta": [
{
"$": 569306, 
"@property": "ot:ottId", 
"@xsi:type": "nex:LiteralMeta"
}, 
{
"$": "Tl69796", 
"@property": "ot:treebaseOTUId", 
"@xsi:type": "nex:LiteralMeta"
}, 
{
"$": "Skeletonema costatum B", 
"@property": "ot:originalLabel", 
"@xsi:type": "nex:LiteralMeta"
}
]
}, 
{
"@about": "#otu412563", 
"@id": "otu412563", 
"@label": "Skeletonema costatum", 
"meta": [
{
"$": 569306, 
"@property": "ot:ottId", 
"@xsi:type": "nex:LiteralMeta"
}, 
{
"$": "Tl69797", 
"@property": "ot:treebaseOTUId", 
"@xsi:type": "nex:LiteralMeta"
}, 
{
"$": "Skeletonema costatum SFB 189", 
"@property": "ot:originalLabel", 
"@xsi:type": "nex:LiteralMeta"
}
]
}, 
{
"@about": "#otu412564", 
"@id": "otu412564", 
"@label": "Skeletonema dohrnii", 
"meta": [
{
"$": 810367, 
"@property": "ot:ottId", 
"@xsi:type": "nex:LiteralMeta"
}, 
{
"$": "Tl69798", 
"@property": "ot:treebaseOTUId", 
"@xsi:type": "nex:LiteralMeta"
}, 
{
"$": "Skeletonema dohrnii B224", 
"@property": "ot:originalLabel", 
"@xsi:type": "nex:LiteralMeta"
}
]
}, 
{
"@about": "#otu412565", 
"@id": "otu412565", 
"@label": "Skeletonema tropicum", 
"meta": [
{
"$": 441574, 
"@property": "ot:ottId", 
"@xsi:type": "nex:LiteralMeta"
}, 
{
"$": "Tl69799", 
"@property": "ot:treebaseOTUId", 
"@xsi:type": "nex:LiteralMeta"
}, 
{
"$": "Skeletonema tropicum MM", 
"@property": "ot:originalLabel", 
"@xsi:type": "nex:LiteralMeta"
}
]
}, 
{
"@about": "#otu412566", 
"@id": "otu412566", 
"@label": "Skeletonema grethae", 
"meta": [
{
"$": 810365, 
"@property": "ot:ottId", 
"@xsi:type": "nex:LiteralMeta"
}, 
{
"$": "Tl69800", 
"@property": "ot:treebaseOTUId", 
"@xsi:type": "nex:LiteralMeta"
}, 
{
"$": "Skeletonema grethae B192", 
"@property": "ot:originalLabel", 
"@xsi:type": "nex:LiteralMeta"
}
]
}, 
{
"@about": "#otu412567", 
"@id": "otu412567", 
"@label": "Skeletonema menzellii", 
"meta": [
{
"$": 322452, 
"@property": "ot:ottId", 
"@xsi:type": "nex:LiteralMeta"
}, 
{
"$": "Tl69801", 
"@property": "ot:treebaseOTUId", 
"@xsi:type": "nex:LiteralMeta"
}, 
{
"$": "Skeletonema menzelii B220", 
"@property": "ot:originalLabel", 
"@xsi:type": "nex:LiteralMeta"
}
]
}, 
{
"@about": "#otu412568", 
"@id": "otu412568", 
"@label": "Skeletonema marinoi", 
"meta": [
{
"$": 810369, 
"@property": "ot:ottId", 
"@xsi:type": "nex:LiteralMeta"
}, 
{
"$": "Tl69802", 
"@property": "ot:treebaseOTUId", 
"@xsi:type": "nex:LiteralMeta"
}, 
{
"$": "Skeletonema marinoi CCMP1332", 
"@property": "ot:originalLabel", 
"@xsi:type": "nex:LiteralMeta"
}
]
}, 
{
"@about": "#otu412569", 
"@id": "otu412569", 
"@label": "Skeletonema japonicum", 
"meta": [
{
"$": 441575, 
"@property": "ot:ottId", 
"@xsi:type": "nex:LiteralMeta"
}, 
{
"$": "Tl69803", 
"@property": "ot:treebaseOTUId", 
"@xsi:type": "nex:LiteralMeta"
}, 
{
"$": "Skeletonema japonicum KoreaCS25", 
"@property": "ot:originalLabel", 
"@xsi:type": "nex:LiteralMeta"
}
]
}, 
{
"@about": "#otu412570", 
"@id": "otu412570", 
"@label": "Skeletonema marinoi", 
"meta": [
{
"$": 810369, 
"@property": "ot:ottId", 
"@xsi:type": "nex:LiteralMeta"
}, 
{
"$": "Tl69804", 
"@property": "ot:treebaseOTUId", 
"@xsi:type": "nex:LiteralMeta"
}, 
{
"$": "Skeletonema marinoi B119", 
"@property": "ot:originalLabel", 
"@xsi:type": "nex:LiteralMeta"
}
]
}, 
{
"@about": "#otu412571", 
"@id": "otu412571", 
"@label": "Skeletonema menzellii", 
"meta": [
{
"$": 322452, 
"@property": "ot:ottId", 
"@xsi:type": "nex:LiteralMeta"
}, 
{
"$": "Tl69805", 
"@property": "ot:treebaseOTUId", 
"@xsi:type": "nex:LiteralMeta"
}, 
{
"$": "Skeletonema menzelii B82", 
"@property": "ot:originalLabel", 
"@xsi:type": "nex:LiteralMeta"
}
]
}, 
{
"@about": "#otu412572", 
"@id": "otu412572", 
"@label": "Skeletonema", 
"meta": [
{
"$": 569303, 
"@property": "ot:ottId", 
"@xsi:type": "nex:LiteralMeta"
}, 
{
"$": "Tl69806", 
"@property": "ot:treebaseOTUId", 
"@xsi:type": "nex:LiteralMeta"
}, 
{
"$": "Skeletonema pseudocortatum Vill", 
"@property": "ot:originalLabel", 
"@xsi:type": "nex:LiteralMeta"
}
]
}, 
{
"@about": "#otu412573", 
"@id": "otu412573", 
"@label": "Skeletonema marinoi", 
"meta": [
{
"$": 810369, 
"@property": "ot:ottId", 
"@xsi:type": "nex:LiteralMeta"
}, 
{
"$": "Tl69807", 
"@property": "ot:treebaseOTUId", 
"@xsi:type": "nex:LiteralMeta"
}, 
{
"$": "Skeletonema marinoi FE47", 
"@property": "ot:originalLabel", 
"@xsi:type": "nex:LiteralMeta"
}
]
}, 
{
"@about": "#otu412574", 
"@id": "otu412574", 
"@label": "Skeletonema marinoi", 
"meta": [
{
"$": 810369, 
"@property": "ot:ottId", 
"@xsi:type": "nex:LiteralMeta"
}, 
{
"$": "Tl69808", 
"@property": "ot:treebaseOTUId", 
"@xsi:type": "nex:LiteralMeta"
}, 
{
"$": "Skeletonema marinoi KAL D2", 
"@property": "ot:originalLabel", 
"@xsi:type": "nex:LiteralMeta"
}
]
}, 
{
"@about": "#otu412575", 
"@id": "otu412575", 
"@label": "Skeletonema marinoi", 
"meta": [
{
"$": 810369, 
"@property": "ot:ottId", 
"@xsi:type": "nex:LiteralMeta"
}, 
{
"$": "Tl69809", 
"@property": "ot:treebaseOTUId", 
"@xsi:type": "nex:LiteralMeta"
}, 
{
"$": "Skeletonema marinoi PORT F3", 
"@property": "ot:originalLabel", 
"@xsi:type": "nex:LiteralMeta"
}
]
}, 
{
"@about": "#otu412576", 
"@id": "otu412576", 
"@label": "Skeletonema marinoi", 
"meta": [
{
"$": 810369, 
"@property": "ot:ottId", 
"@xsi:type": "nex:LiteralMeta"
}, 
{
"$": "Tl69810", 
"@property": "ot:treebaseOTUId", 
"@xsi:type": "nex:LiteralMeta"
}, 
{
"$": "Skeletonema marinoi KAL H3", 
"@property": "ot:originalLabel", 
"@xsi:type": "nex:LiteralMeta"
}
]
}, 
{
"@about": "#otu412577", 
"@id": "otu412577", 
"@label": "Skeletonema tropicum", 
"meta": [
{
"$": 441574, 
"@property": "ot:ottId", 
"@xsi:type": "nex:LiteralMeta"
}, 
{
"$": "Tl69811", 
"@property": "ot:treebaseOTUId", 
"@xsi:type": "nex:LiteralMeta"
}, 
{
"$": "Skeletonema tropicum CS604", 
"@property": "ot:originalLabel", 
"@xsi:type": "nex:LiteralMeta"
}
]
}, 
{
"@about": "#otu412578", 
"@id": "otu412578", 
"@label": "Skeletonema marinoi", 
"meta": [
{
"$": 810369, 
"@property": "ot:ottId", 
"@xsi:type": "nex:LiteralMeta"
}, 
{
"$": "Tl69812", 
"@property": "ot:treebaseOTUId", 
"@xsi:type": "nex:LiteralMeta"
}, 
{
"$": "Skeletonema marinoi FE41", 
"@property": "ot:originalLabel", 
"@xsi:type": "nex:LiteralMeta"
}
]
}, 
{
"@about": "#otu412579", 
"@id": "otu412579", 
"@label": "Skeletonema tropicum", 
"meta": [
{
"$": 441574, 
"@property": "ot:ottId", 
"@xsi:type": "nex:LiteralMeta"
}, 
{
"$": "Tl69813", 
"@property": "ot:treebaseOTUId", 
"@xsi:type": "nex:LiteralMeta"
}, 
{
"$": "Skeletonema tropicum B213", 
"@property": "ot:originalLabel", 
"@xsi:type": "nex:LiteralMeta"
}
]
}, 
{
"@about": "#otu412580", 
"@id": "otu412580", 
"@label": "Skeletonema ardens", 
"meta": [
{
"$": 777867, 
"@property": "ot:ottId", 
"@xsi:type": "nex:LiteralMeta"
}, 
{
"$": "Tl69814", 
"@property": "ot:treebaseOTUId", 
"@xsi:type": "nex:LiteralMeta"
}, 
{
"$": "Skeletonema ardens CS347", 
"@property": "ot:originalLabel", 
"@xsi:type": "nex:LiteralMeta"
}
]
}, 
{
"@about": "#otu412581", 
"@id": "otu412581", 
"@label": "Skeletonema marinoi", 
"meta": [
{
"$": 810369, 
"@property": "ot:ottId", 
"@xsi:type": "nex:LiteralMeta"
}, 
{
"$": "Tl69815", 
"@property": "ot:treebaseOTUId", 
"@xsi:type": "nex:LiteralMeta"
}, 
{
"$": "Skeletonema marinoi RCSKB3", 
"@property": "ot:originalLabel", 
"@xsi:type": "nex:LiteralMeta"
}
]
}, 
{
"@about": "#otu412582", 
"@id": "otu412582", 
"@label": "Skeletonema marinoi", 
"meta": [
{
"$": 810369, 
"@property": "ot:ottId", 
"@xsi:type": "nex:LiteralMeta"
}, 
{
"$": "Tl69816", 
"@property": "ot:treebaseOTUId", 
"@xsi:type": "nex:LiteralMeta"
}, 
{
"$": "Skeletonema marinoi CCMP791", 
"@property": "ot:originalLabel", 
"@xsi:type": "nex:LiteralMeta"
}
]
}, 
{
"@about": "#otu412583", 
"@id": "otu412583", 
"@label": "Skeletonema marinoi", 
"meta": [
{
"$": 810369, 
"@property": "ot:ottId", 
"@xsi:type": "nex:LiteralMeta"
}, 
{
"$": "Tl69817", 
"@property": "ot:treebaseOTUId", 
"@xsi:type": "nex:LiteralMeta"
}, 
{
"$": "Skeletonema marinoi CCMP1016", 
"@property": "ot:originalLabel", 
"@xsi:type": "nex:LiteralMeta"
}
]
}, 
{
"@about": "#otu412584", 
"@id": "otu412584", 
"@label": "Skeletonema marinoi", 
"meta": [
{
"$": 810369, 
"@property": "ot:ottId", 
"@xsi:type": "nex:LiteralMeta"
}, 
{
"$": "Tl69818", 
"@property": "ot:treebaseOTUId", 
"@xsi:type": "nex:LiteralMeta"
}, 
{
"$": "Skeletonema marinoi KAL N3", 
"@property": "ot:originalLabel", 
"@xsi:type": "nex:LiteralMeta"
}
]
}, 
{
"@about": "#otu412585", 
"@id": "otu412585", 
"@label": "Skeletonema marinoi", 
"meta": [
{
"$": 810369, 
"@property": "ot:ottId", 
"@xsi:type": "nex:LiteralMeta"
}, 
{
"$": "Tl69819", 
"@property": "ot:treebaseOTUId", 
"@xsi:type": "nex:LiteralMeta"
}, 
{
"$": "Skeletonema marinoi PLY582", 
"@property": "ot:originalLabel", 
"@xsi:type": "nex:LiteralMeta"
}
]
}, 
{
"@about": "#otu412586", 
"@id": "otu412586", 
"@label": "Skeletonema marinoi", 
"meta": [
{
"$": 810369, 
"@property": "ot:ottId", 
"@xsi:type": "nex:LiteralMeta"
}, 
{
"$": "Tl69820", 
"@property": "ot:treebaseOTUId", 
"@xsi:type": "nex:LiteralMeta"
}, 
{
"$": "Skeletonema marinoi CAN K2", 
"@property": "ot:originalLabel", 
"@xsi:type": "nex:LiteralMeta"
}
]
}
]
}, 
"trees": {
"@id": "trees2774", 
"@otus": "otus2774", 
"tree": []
}
}
}